{
  "dram_cache_size": 2834674688,
  "flash_cache_size": 283467481088,
  "results": [
    {
      "hit": 13600252,
      "iteration": 0,
      "metrics": [
        {
          "admission_treshold": 16,
          "algorithm": "lru",
          "byte_inserted": 14535630848,
          "byte_miss": 4342789621248,
          "byte_read": 460942034944,
          "byte_reinserted": 460942034944,
          "hit": 13600252,
          "inserted": 145170,
          "layer": 0,
          "metrics_time": [
            {
              "byte_inserted": 0,
              "byte_miss": 32768,
              "byte_read": 0,
              "byte_reinserted": 0,
              "hit": 0,
              "inserted": 0,
              "miss_ratio": 1.0,
              "reinserted": 0,
              "req": 1
            },
            {
              "byte_inserted": 57184256,
              "byte_miss": 22216401920,
              "byte_read": 1179525120,
              "byte_reinserted": 1179525120,
              "hit": 66898,
              "inserted": 1427,
              "miss_ratio": 0.8321254705144291,
              "reinserted": 66898,
              "req": 398500
            },
            {
              "byte_inserted": 104947712,
              "byte_miss": 16937430016,
              "byte_read": 2369433600,
              "byte_reinserted": 2369433600,
              "hit": 94927,
              "inserted": 2599,
              "miss_ratio": 0.7479729406829609,
              "reinserted": 94927,
              "req": 376654
            },
            {
              "byte_inserted": 81813504,
              "byte_miss": 20553926144,
              "byte_read": 2866143232,
              "byte_reinserted": 2866143232,
              "hit": 108298,
              "inserted": 1958,
              "miss_ratio": 0.7108583633693766,
              "reinserted": 108298,
              "req": 374550
            },
            {
              "byte_inserted": 45314048,
              "byte_miss": 7871430144,
              "byte_read": 1679724544,
              "byte_reinserted": 1679724544,
              "hit": 66618,
              "inserted": 976,
              "miss_ratio": 0.6710043508536266,
              "reinserted": 66618,
              "req": 202489
            },
            {
              "byte_inserted": 28528640,
              "byte_miss": 16762050560,
              "byte_read": 1538478080,
              "byte_reinserted": 1538478080,
              "hit": 78301,
              "inserted": 610,
              "miss_ratio": 0.6626076690064073,
              "reinserted": 78301,
              "req": 232077
            },
            {
              "byte_inserted": 18903040,
              "byte_miss": 6572981248,
              "byte_read": 1124687872,
              "byte_reinserted": 1124687872,
              "hit": 49979,
              "inserted": 404,
              "miss_ratio": 0.6669643035629802,
              "reinserted": 49979,
              "req": 150071
            },
            {
              "byte_inserted": 16621568,
              "byte_miss": 5911531008,
              "byte_read": 973271040,
              "byte_reinserted": 973271040,
              "hit": 44956,
              "inserted": 383,
              "miss_ratio": 0.6638753476687502,
              "reinserted": 44956,
              "req": 133748
            },
            {
              "byte_inserted": 25776128,
              "byte_miss": 6426826752,
              "byte_read": 1127084032,
              "byte_reinserted": 1127084032,
              "hit": 49311,
              "inserted": 524,
              "miss_ratio": 0.649279155612771,
              "reinserted": 49311,
              "req": 140599
            },
            {
              "byte_inserted": 23408640,
              "byte_miss": 6090566656,
              "byte_read": 1117126656,
              "byte_reinserted": 1117126656,
              "hit": 47103,
              "inserted": 444,
              "miss_ratio": 0.6415978695073236,
              "reinserted": 47103,
              "req": 131425
            },
            {
              "byte_inserted": 21733376,
              "byte_miss": 8878895104,
              "byte_read": 1082949632,
              "byte_reinserted": 1082949632,
              "hit": 44504,
              "inserted": 425,
              "miss_ratio": 0.660818535172624,
              "reinserted": 44504,
              "req": 131210
            },
            {
              "byte_inserted": 16289792,
              "byte_miss": 36075889152,
              "byte_read": 1136312320,
              "byte_reinserted": 1136312320,
              "hit": 47713,
              "inserted": 353,
              "miss_ratio": 0.8022423011563808,
              "reinserted": 47713,
              "req": 241270
            },
            {
              "byte_inserted": 18419712,
              "byte_miss": 34904704000,
              "byte_read": 1159876608,
              "byte_reinserted": 1159876608,
              "hit": 46236,
              "inserted": 425,
              "miss_ratio": 0.8112916457494093,
              "reinserted": 46236,
              "req": 245013
            },
            {
              "byte_inserted": 19415040,
              "byte_miss": 31665496576,
              "byte_read": 1118502912,
              "byte_reinserted": 1118502912,
              "hit": 47945,
              "inserted": 390,
              "miss_ratio": 0.7861850907080041,
              "reinserted": 47945,
              "req": 224236
            },
            {
              "byte_inserted": 15347712,
              "byte_miss": 5048819712,
              "byte_read": 1114570752,
              "byte_reinserted": 1114570752,
              "hit": 44220,
              "inserted": 316,
              "miss_ratio": 0.6064365688246498,
              "reinserted": 44220,
              "req": 112358
            },
            {
              "byte_inserted": 13930496,
              "byte_miss": 4105182720,
              "byte_read": 1010540544,
              "byte_reinserted": 1010540544,
              "hit": 39786,
              "inserted": 270,
              "miss_ratio": 0.6033339647660542,
              "reinserted": 39786,
              "req": 100301
            },
            {
              "byte_inserted": 18092032,
              "byte_miss": 5048037376,
              "byte_read": 1264099328,
              "byte_reinserted": 1264099328,
              "hit": 48618,
              "inserted": 406,
              "miss_ratio": 0.6198838182059843,
              "reinserted": 48618,
              "req": 127903
            },
            {
              "byte_inserted": 20025344,
              "byte_miss": 8204724736,
              "byte_read": 1679724544,
              "byte_reinserted": 1679724544,
              "hit": 62160,
              "inserted": 432,
              "miss_ratio": 0.6472350858076819,
              "reinserted": 62160,
              "req": 176208
            },
            {
              "byte_inserted": 53223424,
              "byte_miss": 33919952384,
              "byte_read": 3350630400,
              "byte_reinserted": 3350630400,
              "hit": 105739,
              "inserted": 1162,
              "miss_ratio": 0.7265090125624956,
              "reinserted": 105739,
              "req": 386627
            },
            {
              "byte_inserted": 95477760,
              "byte_miss": 47376099840,
              "byte_read": 5514477568,
              "byte_reinserted": 5514477568,
              "hit": 167791,
              "inserted": 1879,
              "miss_ratio": 0.70948450645211,
              "reinserted": 167791,
              "req": 577563
            },
            {
              "byte_inserted": 95584256,
              "byte_miss": 50633700352,
              "byte_read": 5367209984,
              "byte_reinserted": 5367209984,
              "hit": 167625,
              "inserted": 1844,
              "miss_ratio": 0.7142401729305108,
              "reinserted": 167625,
              "req": 586594
            },
            {
              "byte_inserted": 81920000,
              "byte_miss": 48091282944,
              "byte_read": 5061464064,
              "byte_reinserted": 5061464064,
              "hit": 156084,
              "inserted": 1564,
              "miss_ratio": 0.7107434340738764,
              "reinserted": 156084,
              "req": 539604
            },
            {
              "byte_inserted": 68149248,
              "byte_miss": 46847634432,
              "byte_read": 4421373952,
              "byte_reinserted": 4421373952,
              "hit": 141775,
              "inserted": 1284,
              "miss_ratio": 0.7181977376312112,
              "reinserted": 141775,
              "req": 503101
            },
            {
              "byte_inserted": 57323520,
              "byte_miss": 42846716416,
              "byte_read": 3663765504,
              "byte_reinserted": 3663765504,
              "hit": 116451,
              "inserted": 1043,
              "miss_ratio": 0.7278183819765662,
              "reinserted": 116451,
              "req": 427843
            },
            {
              "byte_inserted": 67887104,
              "byte_miss": 44928993792,
              "byte_read": 4373315584,
              "byte_reinserted": 4373315584,
              "hit": 136585,
              "inserted": 1234,
              "miss_ratio": 0.714757987549051,
              "reinserted": 136585,
              "req": 478839
            },
            {
              "byte_inserted": 69611520,
              "byte_miss": 47511839744,
              "byte_read": 4450562048,
              "byte_reinserted": 4450562048,
              "hit": 141013,
              "inserted": 1257,
              "miss_ratio": 0.7160625329719672,
              "reinserted": 141013,
              "req": 496634
            },
            {
              "byte_inserted": 78176256,
              "byte_miss": 47818556928,
              "byte_read": 4646146048,
              "byte_reinserted": 4646146048,
              "hit": 146523,
              "inserted": 1339,
              "miss_ratio": 0.7146482252542445,
              "reinserted": 146523,
              "req": 513482
            },
            {
              "byte_inserted": 71737344,
              "byte_miss": 46844289536,
              "byte_read": 3985702912,
              "byte_reinserted": 3985702912,
              "hit": 126164,
              "inserted": 1153,
              "miss_ratio": 0.7230238965543737,
              "reinserted": 126164,
              "req": 455505
            },
            {
              "byte_inserted": 39337984,
              "byte_miss": 37531411968,
              "byte_read": 2331230208,
              "byte_reinserted": 2331230208,
              "hit": 79171,
              "inserted": 659,
              "miss_ratio": 0.7536261650251288,
              "reinserted": 79171,
              "req": 321345
            },
            {
              "byte_inserted": 25088000,
              "byte_miss": 23663698432,
              "byte_read": 1431441408,
              "byte_reinserted": 1431441408,
              "hit": 55596,
              "inserted": 404,
              "miss_ratio": 0.7369979658451205,
              "reinserted": 55596,
              "req": 211390
            },
            {
              "byte_inserted": 19275776,
              "byte_miss": 8700886528,
              "byte_read": 1413943296,
              "byte_reinserted": 1413943296,
              "hit": 56833,
              "inserted": 320,
              "miss_ratio": 0.6429863684904831,
              "reinserted": 56833,
              "req": 159190
            },
            {
              "byte_inserted": 27685376,
              "byte_miss": 6051714048,
              "byte_read": 1390738432,
              "byte_reinserted": 1390738432,
              "hit": 52751,
              "inserted": 448,
              "miss_ratio": 0.6218512093363346,
              "reinserted": 52751,
              "req": 139498
            },
            {
              "byte_inserted": 64905728,
              "byte_miss": 6864273408,
              "byte_read": 1432171008,
              "byte_reinserted": 1432171008,
              "hit": 54898,
              "inserted": 929,
              "miss_ratio": 0.6360562707999098,
              "reinserted": 54898,
              "req": 150842
            },
            {
              "byte_inserted": 44000768,
              "byte_miss": 6231461376,
              "byte_read": 1519045632,
              "byte_reinserted": 1519045632,
              "hit": 54614,
              "inserted": 842,
              "miss_ratio": 0.6070793913450124,
              "reinserted": 54614,
              "req": 138995
            },
            {
              "byte_inserted": 20889600,
              "byte_miss": 4677794816,
              "byte_read": 1322316800,
              "byte_reinserted": 1322316800,
              "hit": 47397,
              "inserted": 408,
              "miss_ratio": 0.5801413790659768,
              "reinserted": 47397,
              "req": 112888
            },
            {
              "byte_inserted": 21794816,
              "byte_miss": 5108358656,
              "byte_read": 1475131904,
              "byte_reinserted": 1475131904,
              "hit": 51990,
              "inserted": 1060,
              "miss_ratio": 0.5669809434968017,
              "reinserted": 51990,
              "req": 120064
            },
            {
              "byte_inserted": 30694912,
              "byte_miss": 5584093696,
              "byte_read": 1657415168,
              "byte_reinserted": 1657415168,
              "hit": 57457,
              "inserted": 1218,
              "miss_ratio": 0.6058487796177645,
              "reinserted": 57457,
              "req": 145774
            },
            {
              "byte_inserted": 19054592,
              "byte_miss": 9049496064,
              "byte_read": 1303090688,
              "byte_reinserted": 1303090688,
              "hit": 47859,
              "inserted": 652,
              "miss_ratio": 0.6323318147946131,
              "reinserted": 47859,
              "req": 130169
            },
            {
              "byte_inserted": 24891392,
              "byte_miss": 34514189824,
              "byte_read": 1306025472,
              "byte_reinserted": 1306025472,
              "hit": 46860,
              "inserted": 1197,
              "miss_ratio": 0.7897825150732127,
              "reinserted": 46860,
              "req": 222912
            },
            {
              "byte_inserted": 24510464,
              "byte_miss": 33163108864,
              "byte_read": 1187520512,
              "byte_reinserted": 1187520512,
              "hit": 42453,
              "inserted": 1130,
              "miss_ratio": 0.7977301639484856,
              "reinserted": 42453,
              "req": 209883
            },
            {
              "byte_inserted": 34955776,
              "byte_miss": 31083561472,
              "byte_read": 1777495552,
              "byte_reinserted": 1777495552,
              "hit": 59229,
              "inserted": 1515,
              "miss_ratio": 0.7503109046376433,
              "reinserted": 59229,
              "req": 237211
            },
            {
              "byte_inserted": 37851136,
              "byte_miss": 6523094016,
              "byte_read": 2127496704,
              "byte_reinserted": 2127496704,
              "hit": 68430,
              "inserted": 1426,
              "miss_ratio": 0.5803308045652746,
              "reinserted": 68430,
              "req": 163057
            },
            {
              "byte_inserted": 90188288,
              "byte_miss": 11575625216,
              "byte_read": 4181983744,
              "byte_reinserted": 4181983744,
              "hit": 119261,
              "inserted": 2604,
              "miss_ratio": 0.582901409435876,
              "reinserted": 119261,
              "req": 285930
            },
            {
              "byte_inserted": 128679936,
              "byte_miss": 19300815360,
              "byte_read": 5887757824,
              "byte_reinserted": 5887757824,
              "hit": 163109,
              "inserted": 3220,
              "miss_ratio": 0.6014002761452084,
              "reinserted": 163109,
              "req": 409205
            },
            {
              "byte_inserted": 130654208,
              "byte_miss": 20778851840,
              "byte_read": 6387859968,
              "byte_reinserted": 6387859968,
              "hit": 177137,
              "inserted": 3530,
              "miss_ratio": 0.6296753907875123,
              "reinserted": 177137,
              "req": 478329
            },
            {
              "byte_inserted": 160162304,
              "byte_miss": 17181977600,
              "byte_read": 6014999040,
              "byte_reinserted": 6014999040,
              "hit": 163393,
              "inserted": 2612,
              "miss_ratio": 0.5902205480345293,
              "reinserted": 163393,
              "req": 398734
            },
            {
              "byte_inserted": 114061312,
              "byte_miss": 19251670016,
              "byte_read": 5157686272,
              "byte_reinserted": 5157686272,
              "hit": 145730,
              "inserted": 2454,
              "miss_ratio": 0.6018131940194107,
              "reinserted": 145730,
              "req": 365984
            },
            {
              "byte_inserted": 97968128,
              "byte_miss": 15292106240,
              "byte_read": 4107358720,
              "byte_reinserted": 4107358720,
              "hit": 121874,
              "inserted": 1386,
              "miss_ratio": 0.6048478874792087,
              "reinserted": 121874,
              "req": 308423
            },
            {
              "byte_inserted": 126627840,
              "byte_miss": 17298061824,
              "byte_read": 4574211584,
              "byte_reinserted": 4574211584,
              "hit": 137397,
              "inserted": 1788,
              "miss_ratio": 0.610480955958439,
              "reinserted": 137397,
              "req": 352735
            },
            {
              "byte_inserted": 110817280,
              "byte_miss": 23532471808,
              "byte_read": 4593033216,
              "byte_reinserted": 4593033216,
              "hit": 146252,
              "inserted": 1612,
              "miss_ratio": 0.6449771938895645,
              "reinserted": 146252,
              "req": 411951
            },
            {
              "byte_inserted": 81641472,
              "byte_miss": 15113304576,
              "byte_read": 4381826560,
              "byte_reinserted": 4381826560,
              "hit": 133651,
              "inserted": 1144,
              "miss_ratio": 0.5950877681974345,
              "reinserted": 133651,
              "req": 330074
            },
            {
              "byte_inserted": 130174976,
              "byte_miss": 16246779904,
              "byte_read": 3814078976,
              "byte_reinserted": 3814078976,
              "hit": 117488,
              "inserted": 1218,
              "miss_ratio": 0.6065463971038857,
              "reinserted": 117488,
              "req": 298607
            },
            {
              "byte_inserted": 43131392,
              "byte_miss": 7496890368,
              "byte_read": 2044964864,
              "byte_reinserted": 2044964864,
              "hit": 71792,
              "inserted": 556,
              "miss_ratio": 0.5712937860529552,
              "reinserted": 71792,
              "req": 167462
            },
            {
              "byte_inserted": 22073344,
              "byte_miss": 16391436800,
              "byte_read": 1357721600,
              "byte_reinserted": 1357721600,
              "hit": 54518,
              "inserted": 295,
              "miss_ratio": 0.684624595787513,
              "reinserted": 54518,
              "req": 172867
            },
            {
              "byte_inserted": 23289856,
              "byte_miss": 34281026560,
              "byte_read": 1125974016,
              "byte_reinserted": 1125974016,
              "hit": 47345,
              "inserted": 329,
              "miss_ratio": 0.785954220560511,
              "reinserted": 47345,
              "req": 221191
            },
            {
              "byte_inserted": 27574784,
              "byte_miss": 33348917248,
              "byte_read": 1258536960,
              "byte_reinserted": 1258536960,
              "hit": 51387,
              "inserted": 308,
              "miss_ratio": 0.7683193493266487,
              "reinserted": 51387,
              "req": 221801
            },
            {
              "byte_inserted": 15523840,
              "byte_miss": 31847439360,
              "byte_read": 1088983040,
              "byte_reinserted": 1088983040,
              "hit": 41113,
              "inserted": 242,
              "miss_ratio": 0.7935659124915896,
              "reinserted": 41113,
              "req": 199158
            },
            {
              "byte_inserted": 12329472,
              "byte_miss": 33764876288,
              "byte_read": 1030918144,
              "byte_reinserted": 1030918144,
              "hit": 43075,
              "inserted": 210,
              "miss_ratio": 0.8039702007399755,
              "reinserted": 43075,
              "req": 219737
            },
            {
              "byte_inserted": 28795392,
              "byte_miss": 33357274624,
              "byte_read": 1055962112,
              "byte_reinserted": 1055962112,
              "hit": 43020,
              "inserted": 296,
              "miss_ratio": 0.8057472094787415,
              "reinserted": 43020,
              "req": 221464
            },
            {
              "byte_inserted": 70092800,
              "byte_miss": 33736209408,
              "byte_read": 1061298688,
              "byte_reinserted": 1061298688,
              "hit": 37786,
              "inserted": 425,
              "miss_ratio": 0.8160969888108552,
              "reinserted": 37786,
              "req": 205467
            },
            {
              "byte_inserted": 29528576,
              "byte_miss": 33185336832,
              "byte_read": 846095360,
              "byte_reinserted": 846095360,
              "hit": 35245,
              "inserted": 273,
              "miss_ratio": 0.8248260437375745,
              "reinserted": 35245,
              "req": 201200
            },
            {
              "byte_inserted": 21836288,
              "byte_miss": 32835631104,
              "byte_read": 801148416,
              "byte_reinserted": 801148416,
              "hit": 35716,
              "inserted": 198,
              "miss_ratio": 0.8154202347298952,
              "reinserted": 35716,
              "req": 193499
            },
            {
              "byte_inserted": 38887936,
              "byte_miss": 32625752576,
              "byte_read": 826101760,
              "byte_reinserted": 826101760,
              "hit": 34689,
              "inserted": 242,
              "miss_ratio": 0.8164981829146367,
              "reinserted": 34689,
              "req": 189039
            },
            {
              "byte_inserted": 22839296,
              "byte_miss": 31442110464,
              "byte_read": 823452160,
              "byte_reinserted": 823452160,
              "hit": 35554,
              "inserted": 213,
              "miss_ratio": 0.8111882912736851,
              "reinserted": 35554,
              "req": 188304
            },
            {
              "byte_inserted": 22507520,
              "byte_miss": 30810331648,
              "byte_read": 936977920,
              "byte_reinserted": 936977920,
              "hit": 37060,
              "inserted": 197,
              "miss_ratio": 0.8130680843766078,
              "reinserted": 37060,
              "req": 198254
            },
            {
              "byte_inserted": 41050112,
              "byte_miss": 32962691072,
              "byte_read": 980012032,
              "byte_reinserted": 980012032,
              "hit": 40610,
              "inserted": 247,
              "miss_ratio": 0.8119114997522104,
              "reinserted": 40610,
              "req": 215909
            },
            {
              "byte_inserted": 16035840,
              "byte_miss": 32953568768,
              "byte_read": 1075088384,
              "byte_reinserted": 1075088384,
              "hit": 42457,
              "inserted": 211,
              "miss_ratio": 0.794078988849603,
              "reinserted": 42457,
              "req": 206181
            },
            {
              "byte_inserted": 25182208,
              "byte_miss": 27952933376,
              "byte_read": 1319187968,
              "byte_reinserted": 1319187968,
              "hit": 50497,
              "inserted": 289,
              "miss_ratio": 0.7690900693685496,
              "reinserted": 50497,
              "req": 218687
            },
            {
              "byte_inserted": 24068096,
              "byte_miss": 5864702464,
              "byte_read": 1264064512,
              "byte_reinserted": 1264064512,
              "hit": 48426,
              "inserted": 247,
              "miss_ratio": 0.5748189121559331,
              "reinserted": 48426,
              "req": 113895
            },
            {
              "byte_inserted": 14077952,
              "byte_miss": 4616741376,
              "byte_read": 1046962176,
              "byte_reinserted": 1046962176,
              "hit": 43159,
              "inserted": 191,
              "miss_ratio": 0.5656650028178085,
              "reinserted": 43159,
              "req": 99368
            },
            {
              "byte_inserted": 21774848,
              "byte_miss": 5317249536,
              "byte_read": 971698176,
              "byte_reinserted": 971698176,
              "hit": 42390,
              "inserted": 238,
              "miss_ratio": 0.5944588479531605,
              "reinserted": 42390,
              "req": 104527
            },
            {
              "byte_inserted": 21413888,
              "byte_miss": 3311720960,
              "byte_read": 916451328,
              "byte_reinserted": 916451328,
              "hit": 38665,
              "inserted": 213,
              "miss_ratio": 0.572247237003684,
              "reinserted": 38665,
              "req": 90391
            },
            {
              "byte_inserted": 30143488,
              "byte_miss": 3247215616,
              "byte_read": 906502656,
              "byte_reinserted": 906502656,
              "hit": 40400,
              "inserted": 465,
              "miss_ratio": 0.5685604442545921,
              "reinserted": 40400,
              "req": 93640
            },
            {
              "byte_inserted": 103498752,
              "byte_miss": 6050121728,
              "byte_read": 1200748544,
              "byte_reinserted": 1200748544,
              "hit": 42537,
              "inserted": 493,
              "miss_ratio": 0.5930758707776491,
              "reinserted": 42537,
              "req": 104533
            },
            {
              "byte_inserted": 106591232,
              "byte_miss": 60146491392,
              "byte_read": 1567606272,
              "byte_reinserted": 1567606272,
              "hit": 48468,
              "inserted": 570,
              "miss_ratio": 0.9166937375924923,
              "reinserted": 48468,
              "req": 581805
            },
            {
              "byte_inserted": 107040768,
              "byte_miss": 129834855936,
              "byte_read": 1549672960,
              "byte_reinserted": 1549672960,
              "hit": 47710,
              "inserted": 753,
              "miss_ratio": 0.959539062486749,
              "reinserted": 47710,
              "req": 1179162
            },
            {
              "byte_inserted": 110542848,
              "byte_miss": 135603048448,
              "byte_read": 1352335360,
              "byte_reinserted": 1352335360,
              "hit": 46464,
              "inserted": 707,
              "miss_ratio": 0.9623386602600889,
              "reinserted": 46464,
              "req": 1233732
            },
            {
              "byte_inserted": 55408128,
              "byte_miss": 126489365504,
              "byte_read": 1186324480,
              "byte_reinserted": 1186324480,
              "hit": 41793,
              "inserted": 488,
              "miss_ratio": 0.9637342297743249,
              "reinserted": 41793,
              "req": 1152409
            },
            {
              "byte_inserted": 93081600,
              "byte_miss": 133675934208,
              "byte_read": 1358372864,
              "byte_reinserted": 1358372864,
              "hit": 42264,
              "inserted": 752,
              "miss_ratio": 0.9651159911452857,
              "reinserted": 42264,
              "req": 1211558
            },
            {
              "byte_inserted": 160211456,
              "byte_miss": 46908840960,
              "byte_read": 1482539008,
              "byte_reinserted": 1482539008,
              "hit": 41087,
              "inserted": 828,
              "miss_ratio": 0.9553424017303501,
              "reinserted": 41087,
              "req": 920045
            },
            {
              "byte_inserted": 118560768,
              "byte_miss": 75902382592,
              "byte_read": 1592855552,
              "byte_reinserted": 1592855552,
              "hit": 45318,
              "inserted": 716,
              "miss_ratio": 0.9548551755466033,
              "reinserted": 45318,
              "req": 1003836
            },
            {
              "byte_inserted": 151837184,
              "byte_miss": 99531856896,
              "byte_read": 1641399296,
              "byte_reinserted": 1641399296,
              "hit": 40808,
              "inserted": 647,
              "miss_ratio": 0.9667135141925164,
              "reinserted": 40808,
              "req": 1225963
            },
            {
              "byte_inserted": 96196608,
              "byte_miss": 13105808384,
              "byte_read": 1397152768,
              "byte_reinserted": 1397152768,
              "hit": 40665,
              "inserted": 542,
              "miss_ratio": 0.9231292709898772,
              "reinserted": 40665,
              "req": 529005
            },
            {
              "byte_inserted": 84948480,
              "byte_miss": 3527451648,
              "byte_read": 1072228864,
              "byte_reinserted": 1072228864,
              "hit": 36543,
              "inserted": 353,
              "miss_ratio": 0.5374479450147462,
              "reinserted": 36543,
              "req": 79003
            },
            {
              "byte_inserted": 51338752,
              "byte_miss": 3596611584,
              "byte_read": 936133632,
              "byte_reinserted": 936133632,
              "hit": 34197,
              "inserted": 260,
              "miss_ratio": 0.5778304507240473,
              "reinserted": 34197,
              "req": 81003
            },
            {
              "byte_inserted": 97574400,
              "byte_miss": 2666237952,
              "byte_read": 882733568,
              "byte_reinserted": 882733568,
              "hit": 31756,
              "inserted": 370,
              "miss_ratio": 0.5132434089515634,
              "reinserted": 31756,
              "req": 65240
            },
            {
              "byte_inserted": 57141248,
              "byte_miss": 2307947520,
              "byte_read": 901507584,
              "byte_reinserted": 901507584,
              "hit": 30305,
              "inserted": 271,
              "miss_ratio": 0.5219277488562865,
              "reinserted": 30305,
              "req": 63390
            },
            {
              "byte_inserted": 42447872,
              "byte_miss": 2688347648,
              "byte_read": 850009600,
              "byte_reinserted": 850009600,
              "hit": 31337,
              "inserted": 212,
              "miss_ratio": 0.5273168818631592,
              "reinserted": 31337,
              "req": 66296
            },
            {
              "byte_inserted": 72163840,
              "byte_miss": 9534136320,
              "byte_read": 1012728320,
              "byte_reinserted": 1012728320,
              "hit": 34619,
              "inserted": 281,
              "miss_ratio": 0.6477369856323009,
              "reinserted": 34619,
              "req": 98276
            },
            {
              "byte_inserted": 124907008,
              "byte_miss": 32086470144,
              "byte_read": 1279473152,
              "byte_reinserted": 1279473152,
              "hit": 39286,
              "inserted": 472,
              "miss_ratio": 0.8016559802090171,
              "reinserted": 39286,
              "req": 198070
            },
            {
              "byte_inserted": 50598912,
              "byte_miss": 31107121152,
              "byte_read": 1063876608,
              "byte_reinserted": 1063876608,
              "hit": 36135,
              "inserted": 258,
              "miss_ratio": 0.8038262965596991,
              "reinserted": 36135,
              "req": 184199
            },
            {
              "byte_inserted": 54597120,
              "byte_miss": 36583875584,
              "byte_read": 1273333248,
              "byte_reinserted": 1273333248,
              "hit": 41494,
              "inserted": 342,
              "miss_ratio": 0.8098053775565395,
              "reinserted": 41494,
              "req": 218166
            },
            {
              "byte_inserted": 86512640,
              "byte_miss": 64393862144,
              "byte_read": 1374278144,
              "byte_reinserted": 1374278144,
              "hit": 46046,
              "inserted": 429,
              "miss_ratio": 0.8632050527916912,
              "reinserted": 46046,
              "req": 336606
            },
            {
              "byte_inserted": 60266496,
              "byte_miss": 60938829312,
              "byte_read": 1320187904,
              "byte_reinserted": 1320187904,
              "hit": 42974,
              "inserted": 364,
              "miss_ratio": 0.863945190560315,
              "reinserted": 42974,
              "req": 315858
            },
            {
              "byte_inserted": 95257600,
              "byte_miss": 56638273536,
              "byte_read": 1288201728,
              "byte_reinserted": 1288201728,
              "hit": 42591,
              "inserted": 455,
              "miss_ratio": 0.8589870081712114,
              "reinserted": 42591,
              "req": 302036
            },
            {
              "byte_inserted": 47173632,
              "byte_miss": 31903238656,
              "byte_read": 1182089728,
              "byte_reinserted": 1182089728,
              "hit": 39404,
              "inserted": 301,
              "miss_ratio": 0.7991815184209319,
              "reinserted": 39404,
              "req": 196217
            },
            {
              "byte_inserted": 91029504,
              "byte_miss": 32714825216,
              "byte_read": 1172790784,
              "byte_reinserted": 1172790784,
              "hit": 39254,
              "inserted": 449,
              "miss_ratio": 0.8070459159346628,
              "reinserted": 39254,
              "req": 203437
            },
            {
              "byte_inserted": 80592896,
              "byte_miss": 32683042816,
              "byte_read": 1252563456,
              "byte_reinserted": 1252563456,
              "hit": 41224,
              "inserted": 436,
              "miss_ratio": 0.8022469322946149,
              "reinserted": 41224,
              "req": 208462
            },
            {
              "byte_inserted": 58786304,
              "byte_miss": 33340860928,
              "byte_read": 1530851328,
              "byte_reinserted": 1530851328,
              "hit": 47343,
              "inserted": 422,
              "miss_ratio": 0.7830581636721059,
              "reinserted": 47343,
              "req": 218229
            },
            {
              "byte_inserted": 104044032,
              "byte_miss": 33177575936,
              "byte_read": 1538850816,
              "byte_reinserted": 1538850816,
              "hit": 47397,
              "inserted": 484,
              "miss_ratio": 0.7837501197662163,
              "reinserted": 47397,
              "req": 219177
            },
            {
              "byte_inserted": 71279104,
              "byte_miss": 4190499840,
              "byte_read": 1485614080,
              "byte_reinserted": 1485614080,
              "hit": 46922,
              "inserted": 395,
              "miss_ratio": 0.5457915880160689,
              "reinserted": 46922,
              "req": 103305
            },
            {
              "byte_inserted": 109916160,
              "byte_miss": 5412166144,
              "byte_read": 1587612160,
              "byte_reinserted": 1587612160,
              "hit": 52663,
              "inserted": 517,
              "miss_ratio": 0.5393409784728964,
              "reinserted": 52663,
              "req": 114321
            },
            {
              "byte_inserted": 113733632,
              "byte_miss": 5415296000,
              "byte_read": 1806692352,
              "byte_reinserted": 1806692352,
              "hit": 59943,
              "inserted": 584,
              "miss_ratio": 0.5390772779700115,
              "reinserted": 59943,
              "req": 130050
            },
            {
              "byte_inserted": 97723904,
              "byte_miss": 5217809408,
              "byte_read": 1692998144,
              "byte_reinserted": 1692998144,
              "hit": 56269,
              "inserted": 519,
              "miss_ratio": 0.5403572974783326,
              "reinserted": 56269,
              "req": 122419
            },
            {
              "byte_inserted": 79133696,
              "byte_miss": 4640431104,
              "byte_read": 2085906432,
              "byte_reinserted": 2085906432,
              "hit": 61922,
              "inserted": 510,
              "miss_ratio": 0.5170229859058256,
              "reinserted": 61922,
              "req": 128209
            },
            {
              "byte_inserted": 86334464,
              "byte_miss": 4320540160,
              "byte_read": 1635235840,
              "byte_reinserted": 1635235840,
              "hit": 51996,
              "inserted": 428,
              "miss_ratio": 0.5250205535763223,
              "reinserted": 51996,
              "req": 109470
            },
            {
              "byte_inserted": 83763712,
              "byte_miss": 4089422848,
              "byte_read": 1483591680,
              "byte_reinserted": 1483591680,
              "hit": 49298,
              "inserted": 426,
              "miss_ratio": 0.5191611801999512,
              "reinserted": 49298,
              "req": 102525
            },
            {
              "byte_inserted": 56407040,
              "byte_miss": 6750521344,
              "byte_read": 1370210816,
              "byte_reinserted": 1370210816,
              "hit": 41975,
              "inserted": 352,
              "miss_ratio": 0.6003636952195976,
              "reinserted": 41975,
              "req": 105033
            },
            {
              "byte_inserted": 93496320,
              "byte_miss": 4762257920,
              "byte_read": 1616617472,
              "byte_reinserted": 1616617472,
              "hit": 54276,
              "inserted": 450,
              "miss_ratio": 0.5428080460931972,
              "reinserted": 54276,
              "req": 118716
            },
            {
              "byte_inserted": 87118848,
              "byte_miss": 3328706560,
              "byte_read": 1575190528,
              "byte_reinserted": 1575190528,
              "hit": 50775,
              "inserted": 436,
              "miss_ratio": 0.5087985759753891,
              "reinserted": 50775,
              "req": 103369
            },
            {
              "byte_inserted": 63148032,
              "byte_miss": 3436066304,
              "byte_read": 1569566720,
              "byte_reinserted": 1569566720,
              "hit": 50328,
              "inserted": 373,
              "miss_ratio": 0.518383126949798,
              "reinserted": 50328,
              "req": 104498
            },
            {
              "byte_inserted": 42790912,
              "byte_miss": 3763571200,
              "byte_read": 1531023360,
              "byte_reinserted": 1531023360,
              "hit": 49537,
              "inserted": 339,
              "miss_ratio": 0.5167169100789261,
              "reinserted": 49537,
              "req": 102501
            },
            {
              "byte_inserted": 62653952,
              "byte_miss": 5294093312,
              "byte_read": 1687455744,
              "byte_reinserted": 1687455744,
              "hit": 54188,
              "inserted": 392,
              "miss_ratio": 0.6092615426770791,
              "reinserted": 54188,
              "req": 138681
            },
            {
              "byte_inserted": 93083136,
              "byte_miss": 7283155968,
              "byte_read": 2860094464,
              "byte_reinserted": 2860094464,
              "hit": 80155,
              "inserted": 762,
              "miss_ratio": 0.6188956985208465,
              "reinserted": 80155,
              "req": 210323
            },
            {
              "byte_inserted": 325336064,
              "byte_miss": 11031855616,
              "byte_read": 5013139456,
              "byte_reinserted": 5013139456,
              "hit": 127082,
              "inserted": 1672,
              "miss_ratio": 0.5840237248079396,
              "reinserted": 127082,
              "req": 305503
            },
            {
              "byte_inserted": 451140096,
              "byte_miss": 19928034304,
              "byte_read": 8042223616,
              "byte_reinserted": 8042223616,
              "hit": 192173,
              "inserted": 2608,
              "miss_ratio": 0.5769425512055089,
              "reinserted": 192173,
              "req": 454248
            },
            {
              "byte_inserted": 425072128,
              "byte_miss": 19034032128,
              "byte_read": 7454798336,
              "byte_reinserted": 7454798336,
              "hit": 181692,
              "inserted": 2330,
              "miss_ratio": 0.5970351839037633,
              "reinserted": 181692,
              "req": 450888
            },
            {
              "byte_inserted": 269691904,
              "byte_miss": 19665121792,
              "byte_read": 8129354240,
              "byte_reinserted": 8129354240,
              "hit": 201144,
              "inserted": 2070,
              "miss_ratio": 0.5715180408747556,
              "reinserted": 201144,
              "req": 469434
            },
            {
              "byte_inserted": 235210240,
              "byte_miss": 22666762752,
              "byte_read": 6441957376,
              "byte_reinserted": 6441957376,
              "hit": 167016,
              "inserted": 1697,
              "miss_ratio": 0.60449740461486,
              "reinserted": 167016,
              "req": 422288
            },
            {
              "byte_inserted": 183511040,
              "byte_miss": 40570424832,
              "byte_read": 4923480576,
              "byte_reinserted": 4923480576,
              "hit": 129325,
              "inserted": 1378,
              "miss_ratio": 0.6842682200369137,
              "reinserted": 129325,
              "req": 409604
            },
            {
              "byte_inserted": 225957888,
              "byte_miss": 42587551232,
              "byte_read": 5775272448,
              "byte_reinserted": 5775272448,
              "hit": 148303,
              "inserted": 1561,
              "miss_ratio": 0.6710270049644415,
              "reinserted": 148303,
              "req": 450806
            },
            {
              "byte_inserted": 216802816,
              "byte_miss": 36946816000,
              "byte_read": 6558386688,
              "byte_reinserted": 6558386688,
              "hit": 155630,
              "inserted": 1608,
              "miss_ratio": 0.6522203550422797,
              "reinserted": 155630,
              "req": 447496
            },
            {
              "byte_inserted": 172303360,
              "byte_miss": 13951717376,
              "byte_read": 5970936320,
              "byte_reinserted": 5970936320,
              "hit": 154567,
              "inserted": 1446,
              "miss_ratio": 0.5704240813978372,
              "reinserted": 154567,
              "req": 359813
            },
            {
              "byte_inserted": 147695104,
              "byte_miss": 15714083840,
              "byte_read": 4626124800,
              "byte_reinserted": 4626124800,
              "hit": 123987,
              "inserted": 1124,
              "miss_ratio": 0.5917679945475558,
              "reinserted": 123987,
              "req": 303717
            },
            {
              "byte_inserted": 74536960,
              "byte_miss": 35937410048,
              "byte_read": 2729675264,
              "byte_reinserted": 2729675264,
              "hit": 80632,
              "inserted": 683,
              "miss_ratio": 0.7275807895670389,
              "reinserted": 80632,
              "req": 295985
            },
            {
              "byte_inserted": 75845632,
              "byte_miss": 33748337152,
              "byte_read": 1913375232,
              "byte_reinserted": 1913375232,
              "hit": 59330,
              "inserted": 524,
              "miss_ratio": 0.756426993784434,
              "reinserted": 59330,
              "req": 243582
            },
            {
              "byte_inserted": 55189504,
              "byte_miss": 32259046400,
              "byte_read": 1852089344,
              "byte_reinserted": 1852089344,
              "hit": 58419,
              "inserted": 525,
              "miss_ratio": 0.7542456659921839,
              "reinserted": 58419,
              "req": 237713
            },
            {
              "byte_inserted": 55006208,
              "byte_miss": 34828034560,
              "byte_read": 1822514176,
              "byte_reinserted": 1822514176,
              "hit": 58248,
              "inserted": 510,
              "miss_ratio": 0.7645365759006533,
              "reinserted": 58248,
              "req": 247376
            },
            {
              "byte_inserted": 70763008,
              "byte_miss": 33084644352,
              "byte_read": 1785876992,
              "byte_reinserted": 1785876992,
              "hit": 55669,
              "inserted": 546,
              "miss_ratio": 0.7608596663058234,
              "reinserted": 55669,
              "req": 232788
            },
            {
              "byte_inserted": 71354880,
              "byte_miss": 32713190400,
              "byte_read": 1696340480,
              "byte_reinserted": 1696340480,
              "hit": 52477,
              "inserted": 506,
              "miss_ratio": 0.7685362432625552,
              "reinserted": 52477,
              "req": 226718
            },
            {
              "byte_inserted": 35426816,
              "byte_miss": 31810396160,
              "byte_read": 1309692416,
              "byte_reinserted": 1309692416,
              "hit": 45171,
              "inserted": 355,
              "miss_ratio": 0.7827492172507827,
              "reinserted": 45171,
              "req": 207921
            },
            {
              "byte_inserted": 41829888,
              "byte_miss": 34314638336,
              "byte_read": 1611231232,
              "byte_reinserted": 1611231232,
              "hit": 54498,
              "inserted": 430,
              "miss_ratio": 0.7637526985200406,
              "reinserted": 54498,
              "req": 230682
            },
            {
              "byte_inserted": 47505920,
              "byte_miss": 31880868864,
              "byte_read": 1497464832,
              "byte_reinserted": 1497464832,
              "hit": 48577,
              "inserted": 439,
              "miss_ratio": 0.7822147500560412,
              "reinserted": 48577,
              "req": 223050
            },
            {
              "byte_inserted": 107112960,
              "byte_miss": 32459484160,
              "byte_read": 1505997312,
              "byte_reinserted": 1505997312,
              "hit": 46985,
              "inserted": 607,
              "miss_ratio": 0.7793178274184155,
              "reinserted": 46985,
              "req": 212908
            },
            {
              "byte_inserted": 79216640,
              "byte_miss": 31147546112,
              "byte_read": 1367864832,
              "byte_reinserted": 1367864832,
              "hit": 39496,
              "inserted": 522,
              "miss_ratio": 0.7969127613406144,
              "reinserted": 39496,
              "req": 194478
            },
            {
              "byte_inserted": 49156608,
              "byte_miss": 8031025664,
              "byte_read": 1373155328,
              "byte_reinserted": 1373155328,
              "hit": 45056,
              "inserted": 407,
              "miss_ratio": 0.6151395307121319,
              "reinserted": 45056,
              "req": 117071
            },
            {
              "byte_inserted": 36393472,
              "byte_miss": 3697090048,
              "byte_read": 1529241088,
              "byte_reinserted": 1529241088,
              "hit": 48931,
              "inserted": 366,
              "miss_ratio": 0.546140931815863,
              "reinserted": 48931,
              "req": 107811
            },
            {
              "byte_inserted": 44503552,
              "byte_miss": 5265251328,
              "byte_read": 2275432960,
              "byte_reinserted": 2275432960,
              "hit": 67945,
              "inserted": 533,
              "miss_ratio": 0.5518878812860676,
              "reinserted": 67945,
              "req": 151625
            },
            {
              "byte_inserted": 121127424,
              "byte_miss": 13588811264,
              "byte_read": 5543120384,
              "byte_reinserted": 5543120384,
              "hit": 142284,
              "inserted": 1291,
              "miss_ratio": 0.5718193554599924,
              "reinserted": 142284,
              "req": 332299
            },
            {
              "byte_inserted": 191086592,
              "byte_miss": 18113845248,
              "byte_read": 8617467904,
              "byte_reinserted": 8617467904,
              "hit": 206207,
              "inserted": 1922,
              "miss_ratio": 0.5695600351520996,
              "reinserted": 206207,
              "req": 479061
            },
            {
              "byte_inserted": 184411648,
              "byte_miss": 19010092544,
              "byte_read": 9032939008,
              "byte_reinserted": 9032939008,
              "hit": 215796,
              "inserted": 1835,
              "miss_ratio": 0.5664422491576809,
              "reinserted": 215796,
              "req": 497733
            },
            {
              "byte_inserted": 171881472,
              "byte_miss": 16131856896,
              "byte_read": 7269494784,
              "byte_reinserted": 7269494784,
              "hit": 178189,
              "inserted": 1642,
              "miss_ratio": 0.5645217263795884,
              "reinserted": 178189,
              "req": 409180
            },
            {
              "byte_inserted": 145608704,
              "byte_miss": 15717217280,
              "byte_read": 6114971648,
              "byte_reinserted": 6114971648,
              "hit": 156054,
              "inserted": 1392,
              "miss_ratio": 0.5671214941345841,
              "reinserted": 156054,
              "req": 360503
            },
            {
              "byte_inserted": 106844160,
              "byte_miss": 9990037504,
              "byte_read": 5045575680,
              "byte_reinserted": 5045575680,
              "hit": 128153,
              "inserted": 1099,
              "miss_ratio": 0.554738286746695,
              "reinserted": 128153,
              "req": 287815
            },
            {
              "byte_inserted": 143155200,
              "byte_miss": 14907938816,
              "byte_read": 6406262784,
              "byte_reinserted": 6406262784,
              "hit": 161522,
              "inserted": 1396,
              "miss_ratio": 0.5627710315032672,
              "reinserted": 161522,
              "req": 369422
            },
            {
              "byte_inserted": 132288512,
              "byte_miss": 19174235136,
              "byte_read": 6535409664,
              "byte_reinserted": 6535409664,
              "hit": 161501,
              "inserted": 1346,
              "miss_ratio": 0.5854569442590634,
              "reinserted": 161501,
              "req": 389588
            },
            {
              "byte_inserted": 151674880,
              "byte_miss": 43140810752,
              "byte_read": 6696919552,
              "byte_reinserted": 6696919552,
              "hit": 164334,
              "inserted": 1457,
              "miss_ratio": 0.6553592812487548,
              "reinserted": 164334,
              "req": 476827
            },
            {
              "byte_inserted": 119164928,
              "byte_miss": 45172616704,
              "byte_read": 5708713984,
              "byte_reinserted": 5708713984,
              "hit": 143721,
              "inserted": 1176,
              "miss_ratio": 0.6753960402748228,
              "reinserted": 143721,
              "req": 442758
            },
            {
              "byte_inserted": 64147968,
              "byte_miss": 30832751616,
              "byte_read": 2828399104,
              "byte_reinserted": 2828399104,
              "hit": 79586,
              "inserted": 604,
              "miss_ratio": 0.7061034874961225,
              "reinserted": 79586,
              "req": 270796
            },
            {
              "byte_inserted": 38277120,
              "byte_miss": 5877343232,
              "byte_read": 2009944064,
              "byte_reinserted": 2009944064,
              "hit": 63260,
              "inserted": 421,
              "miss_ratio": 0.5634320890526766,
              "reinserted": 63260,
              "req": 144903
            },
            {
              "byte_inserted": 32887296,
              "byte_miss": 4107566592,
              "byte_read": 1802404864,
              "byte_reinserted": 1802404864,
              "hit": 55532,
              "inserted": 363,
              "miss_ratio": 0.5453265212549945,
              "reinserted": 55532,
              "req": 122136
            },
            {
              "byte_inserted": 38989824,
              "byte_miss": 4429148672,
              "byte_read": 1890717696,
              "byte_reinserted": 1890717696,
              "hit": 58680,
              "inserted": 436,
              "miss_ratio": 0.5601265348345602,
              "reinserted": 58680,
              "req": 133402
            },
            {
              "byte_inserted": 36335616,
              "byte_miss": 4597593600,
              "byte_read": 1791115264,
              "byte_reinserted": 1791115264,
              "hit": 58430,
              "inserted": 389,
              "miss_ratio": 0.5416895442779825,
              "reinserted": 58430,
              "req": 127490
            },
            {
              "byte_inserted": 30826496,
              "byte_miss": 4494242816,
              "byte_read": 1699102720,
              "byte_reinserted": 1699102720,
              "hit": 56082,
              "inserted": 332,
              "miss_ratio": 0.5375938919716696,
              "reinserted": 56082,
              "req": 121283
            },
            {
              "byte_inserted": 32960512,
              "byte_miss": 3739510784,
              "byte_read": 1506791424,
              "byte_reinserted": 1506791424,
              "hit": 50731,
              "inserted": 362,
              "miss_ratio": 0.5245900103083123,
              "reinserted": 50731,
              "req": 106710
            },
            {
              "byte_inserted": 32096256,
              "byte_miss": 5106345984,
              "byte_read": 1554917376,
              "byte_reinserted": 1554917376,
              "hit": 54532,
              "inserted": 379,
              "miss_ratio": 0.5298317009242655,
              "reinserted": 54532,
              "req": 115984
            },
            {
              "byte_inserted": 21393408,
              "byte_miss": 2890514944,
              "byte_read": 1339031552,
              "byte_reinserted": 1339031552,
              "hit": 45756,
              "inserted": 265,
              "miss_ratio": 0.5411874417158844,
              "reinserted": 45756,
              "req": 99727
            },
            {
              "byte_inserted": 31340032,
              "byte_miss": 3068439040,
              "byte_read": 1469429248,
              "byte_reinserted": 1469429248,
              "hit": 47897,
              "inserted": 349,
              "miss_ratio": 0.5122256734049595,
              "reinserted": 47897,
              "req": 98195
            },
            {
              "byte_inserted": 22765568,
              "byte_miss": 3307332096,
              "byte_read": 1372418048,
              "byte_reinserted": 1372418048,
              "hit": 45928,
              "inserted": 271,
              "miss_ratio": 0.5245204103817047,
              "reinserted": 45928,
              "req": 96593
            },
            {
              "byte_inserted": 57864192,
              "byte_miss": 28550763008,
              "byte_read": 1662361600,
              "byte_reinserted": 1662361600,
              "hit": 50016,
              "inserted": 469,
              "miss_ratio": 0.7503257207038563,
              "reinserted": 50016,
              "req": 200325
            },
            {
              "byte_inserted": 67579904,
              "byte_miss": 32611955712,
              "byte_read": 1839067136,
              "byte_reinserted": 1839067136,
              "hit": 51638,
              "inserted": 551,
              "miss_ratio": 0.769488650313595,
              "reinserted": 51638,
              "req": 224015
            },
            {
              "byte_inserted": 76369920,
              "byte_miss": 35901924864,
              "byte_read": 2827706368,
              "byte_reinserted": 2827706368,
              "hit": 78576,
              "inserted": 706,
              "miss_ratio": 0.7306264334125245,
              "reinserted": 78576,
              "req": 291699
            },
            {
              "byte_inserted": 135888896,
              "byte_miss": 39889593344,
              "byte_read": 5817381376,
              "byte_reinserted": 5817381376,
              "hit": 137783,
              "inserted": 1224,
              "miss_ratio": 0.6764875075429035,
              "reinserted": 137783,
              "req": 425897
            },
            {
              "byte_inserted": 439161856,
              "byte_miss": 48276071936,
              "byte_read": 8670256128,
              "byte_reinserted": 8670256128,
              "hit": 196954,
              "inserted": 2668,
              "miss_ratio": 0.6456807935725517,
              "reinserted": 196954,
              "req": 555866
            },
            {
              "byte_inserted": 278358528,
              "byte_miss": 47752264704,
              "byte_read": 8370529280,
              "byte_reinserted": 8370529280,
              "hit": 191315,
              "inserted": 2055,
              "miss_ratio": 0.6517385313001167,
              "reinserted": 191315,
              "req": 549343
            },
            {
              "byte_inserted": 210961408,
              "byte_miss": 45661617664,
              "byte_read": 8073291776,
              "byte_reinserted": 8073291776,
              "hit": 188539,
              "inserted": 1743,
              "miss_ratio": 0.6525555381510932,
              "reinserted": 188539,
              "req": 542645
            },
            {
              "byte_inserted": 211161088,
              "byte_miss": 45650618368,
              "byte_read": 7194218496,
              "byte_reinserted": 7194218496,
              "hit": 171689,
              "inserted": 1760,
              "miss_ratio": 0.6658238738107473,
              "reinserted": 171689,
              "req": 513768
            },
            {
              "byte_inserted": 186929664,
              "byte_miss": 40850414592,
              "byte_read": 5732019200,
              "byte_reinserted": 5732019200,
              "hit": 141079,
              "inserted": 1488,
              "miss_ratio": 0.6764398962435296,
              "reinserted": 141079,
              "req": 436021
            },
            {
              "byte_inserted": 208191488,
              "byte_miss": 43280496640,
              "byte_read": 6764210688,
              "byte_reinserted": 6764210688,
              "hit": 160026,
              "inserted": 1687,
              "miss_ratio": 0.6640290231761314,
              "reinserted": 160026,
              "req": 476309
            },
            {
              "byte_inserted": 266563584,
              "byte_miss": 45582836224,
              "byte_read": 7719997440,
              "byte_reinserted": 7719997440,
              "hit": 181334,
              "inserted": 2086,
              "miss_ratio": 0.6568951522112206,
              "reinserted": 181334,
              "req": 528509
            }
          ],
          "miss_ratio": 0.7259280684540004,
          "reinserted": 13600252,
          "req": 49622929
        }
      ],
      "miss_ratio": 0.7259280684540004,
      "req": 49622929
    }
  ],
  "trace": "w09.oracleGeneral.bin.zst"
}