{
  "dram_cache_size": 125001,
  "flash_cache_size": 500005,
  "results": [
    {
      "hit": 16080461,
      "iteration": 0,
      "metrics": [
        {
          "admission_treshold": 0,
          "algorithm": "lru",
          "byte_inserted": 43758478,
          "byte_miss": 43758478,
          "byte_read": 6241522,
          "byte_reinserted": 6241522,
          "hit": 6241522,
          "inserted": 43758478,
          "layer": 0,
          "metrics_time": [
            {
              "byte_inserted": 529109,
              "byte_miss": 529109,
              "byte_read": 66130,
              "byte_reinserted": 66130,
              "hit": 66130,
              "inserted": 529109,
              "miss_ratio": 0.8889017688693113,
              "reinserted": 66130,
              "req": 595239
            },
            {
              "byte_inserted": 521187,
              "byte_miss": 521187,
              "byte_read": 74051,
              "byte_reinserted": 74051,
              "hit": 74051,
              "inserted": 521187,
              "miss_ratio": 0.875594300095088,
              "reinserted": 74051,
              "req": 595238
            },
            {
              "byte_inserted": 520836,
              "byte_miss": 520836,
              "byte_read": 74402,
              "byte_reinserted": 74402,
              "hit": 74402,
              "inserted": 520836,
              "miss_ratio": 0.8750046200007392,
              "reinserted": 74402,
              "req": 595238
            },
            {
              "byte_inserted": 520846,
              "byte_miss": 520846,
              "byte_read": 74392,
              "byte_reinserted": 74392,
              "hit": 74392,
              "inserted": 520846,
              "miss_ratio": 0.8750214200034272,
              "reinserted": 74392,
              "req": 595238
            },
            {
              "byte_inserted": 520831,
              "byte_miss": 520831,
              "byte_read": 74407,
              "byte_reinserted": 74407,
              "hit": 74407,
              "inserted": 520831,
              "miss_ratio": 0.8749962199993953,
              "reinserted": 74407,
              "req": 595238
            },
            {
              "byte_inserted": 521254,
              "byte_miss": 521254,
              "byte_read": 73984,
              "byte_reinserted": 73984,
              "hit": 73984,
              "inserted": 521254,
              "miss_ratio": 0.8757068601130976,
              "reinserted": 73984,
              "req": 595238
            },
            {
              "byte_inserted": 521302,
              "byte_miss": 521302,
              "byte_read": 73936,
              "byte_reinserted": 73936,
              "hit": 73936,
              "inserted": 521302,
              "miss_ratio": 0.875787500126,
              "reinserted": 73936,
              "req": 595238
            },
            {
              "byte_inserted": 521083,
              "byte_miss": 521083,
              "byte_read": 74155,
              "byte_reinserted": 74155,
              "hit": 74155,
              "inserted": 521083,
              "miss_ratio": 0.8754195800671328,
              "reinserted": 74155,
              "req": 595238
            },
            {
              "byte_inserted": 520943,
              "byte_miss": 520943,
              "byte_read": 74295,
              "byte_reinserted": 74295,
              "hit": 74295,
              "inserted": 520943,
              "miss_ratio": 0.8751843800295008,
              "reinserted": 74295,
              "req": 595238
            },
            {
              "byte_inserted": 520927,
              "byte_miss": 520927,
              "byte_read": 74311,
              "byte_reinserted": 74311,
              "hit": 74311,
              "inserted": 520927,
              "miss_ratio": 0.8751575000252,
              "reinserted": 74311,
              "req": 595238
            },
            {
              "byte_inserted": 520711,
              "byte_miss": 520711,
              "byte_read": 74528,
              "byte_reinserted": 74528,
              "hit": 74528,
              "inserted": 520711,
              "miss_ratio": 0.8747931503144115,
              "reinserted": 74528,
              "req": 595239
            },
            {
              "byte_inserted": 520433,
              "byte_miss": 520433,
              "byte_read": 74805,
              "byte_reinserted": 74805,
              "hit": 74805,
              "inserted": 520433,
              "miss_ratio": 0.8743275798924128,
              "reinserted": 74805,
              "req": 595238
            },
            {
              "byte_inserted": 521040,
              "byte_miss": 521040,
              "byte_read": 74198,
              "byte_reinserted": 74198,
              "hit": 74198,
              "inserted": 521040,
              "miss_ratio": 0.8753473400555745,
              "reinserted": 74198,
              "req": 595238
            },
            {
              "byte_inserted": 520761,
              "byte_miss": 520761,
              "byte_read": 74477,
              "byte_reinserted": 74477,
              "hit": 74477,
              "inserted": 520761,
              "miss_ratio": 0.8748786199805791,
              "reinserted": 74477,
              "req": 595238
            },
            {
              "byte_inserted": 520807,
              "byte_miss": 520807,
              "byte_read": 74431,
              "byte_reinserted": 74431,
              "hit": 74431,
              "inserted": 520807,
              "miss_ratio": 0.874955899992944,
              "reinserted": 74431,
              "req": 595238
            },
            {
              "byte_inserted": 520971,
              "byte_miss": 520971,
              "byte_read": 74267,
              "byte_reinserted": 74267,
              "hit": 74267,
              "inserted": 520971,
              "miss_ratio": 0.8752314200370273,
              "reinserted": 74267,
              "req": 595238
            },
            {
              "byte_inserted": 520969,
              "byte_miss": 520969,
              "byte_read": 74269,
              "byte_reinserted": 74269,
              "hit": 74269,
              "inserted": 520969,
              "miss_ratio": 0.8752280600364896,
              "reinserted": 74269,
              "req": 595238
            },
            {
              "byte_inserted": 520952,
              "byte_miss": 520952,
              "byte_read": 74286,
              "byte_reinserted": 74286,
              "hit": 74286,
              "inserted": 520952,
              "miss_ratio": 0.87519950003192,
              "reinserted": 74286,
              "req": 595238
            },
            {
              "byte_inserted": 521055,
              "byte_miss": 521055,
              "byte_read": 74183,
              "byte_reinserted": 74183,
              "hit": 74183,
              "inserted": 521055,
              "miss_ratio": 0.8753725400596064,
              "reinserted": 74183,
              "req": 595238
            },
            {
              "byte_inserted": 520899,
              "byte_miss": 520899,
              "byte_read": 74339,
              "byte_reinserted": 74339,
              "hit": 74339,
              "inserted": 520899,
              "miss_ratio": 0.8751104600176736,
              "reinserted": 74339,
              "req": 595238
            },
            {
              "byte_inserted": 520925,
              "byte_miss": 520925,
              "byte_read": 74313,
              "byte_reinserted": 74313,
              "hit": 74313,
              "inserted": 520925,
              "miss_ratio": 0.8751541400246624,
              "reinserted": 74313,
              "req": 595238
            },
            {
              "byte_inserted": 520658,
              "byte_miss": 520658,
              "byte_read": 74581,
              "byte_reinserted": 74581,
              "hit": 74581,
              "inserted": 520658,
              "miss_ratio": 0.8747041104497522,
              "reinserted": 74581,
              "req": 595239
            },
            {
              "byte_inserted": 520733,
              "byte_miss": 520733,
              "byte_read": 74505,
              "byte_reinserted": 74505,
              "hit": 74505,
              "inserted": 520733,
              "miss_ratio": 0.8748315799730528,
              "reinserted": 74505,
              "req": 595238
            },
            {
              "byte_inserted": 520440,
              "byte_miss": 520440,
              "byte_read": 74798,
              "byte_reinserted": 74798,
              "hit": 74798,
              "inserted": 520440,
              "miss_ratio": 0.8743393398942944,
              "reinserted": 74798,
              "req": 595238
            },
            {
              "byte_inserted": 520305,
              "byte_miss": 520305,
              "byte_read": 74933,
              "byte_reinserted": 74933,
              "hit": 74933,
              "inserted": 520305,
              "miss_ratio": 0.8741125398580064,
              "reinserted": 74933,
              "req": 595238
            },
            {
              "byte_inserted": 520965,
              "byte_miss": 520965,
              "byte_read": 74273,
              "byte_reinserted": 74273,
              "hit": 74273,
              "inserted": 520965,
              "miss_ratio": 0.8752213400354144,
              "reinserted": 74273,
              "req": 595238
            },
            {
              "byte_inserted": 520785,
              "byte_miss": 520785,
              "byte_read": 74453,
              "byte_reinserted": 74453,
              "hit": 74453,
              "inserted": 520785,
              "miss_ratio": 0.8749189399870304,
              "reinserted": 74453,
              "req": 595238
            },
            {
              "byte_inserted": 520926,
              "byte_miss": 520926,
              "byte_read": 74312,
              "byte_reinserted": 74312,
              "hit": 74312,
              "inserted": 520926,
              "miss_ratio": 0.8751558200249312,
              "reinserted": 74312,
              "req": 595238
            },
            {
              "byte_inserted": 521296,
              "byte_miss": 521296,
              "byte_read": 73942,
              "byte_reinserted": 73942,
              "hit": 73942,
              "inserted": 521296,
              "miss_ratio": 0.8757774201243872,
              "reinserted": 73942,
              "req": 595238
            },
            {
              "byte_inserted": 520760,
              "byte_miss": 520760,
              "byte_read": 74478,
              "byte_reinserted": 74478,
              "hit": 74478,
              "inserted": 520760,
              "miss_ratio": 0.8748769399803105,
              "reinserted": 74478,
              "req": 595238
            },
            {
              "byte_inserted": 520813,
              "byte_miss": 520813,
              "byte_read": 74425,
              "byte_reinserted": 74425,
              "hit": 74425,
              "inserted": 520813,
              "miss_ratio": 0.8749659799945568,
              "reinserted": 74425,
              "req": 595238
            },
            {
              "byte_inserted": 520322,
              "byte_miss": 520322,
              "byte_read": 74917,
              "byte_reinserted": 74917,
              "hit": 74917,
              "inserted": 520322,
              "miss_ratio": 0.8741396313077604,
              "reinserted": 74917,
              "req": 595239
            },
            {
              "byte_inserted": 520760,
              "byte_miss": 520760,
              "byte_read": 74478,
              "byte_reinserted": 74478,
              "hit": 74478,
              "inserted": 520760,
              "miss_ratio": 0.8748769399803105,
              "reinserted": 74478,
              "req": 595238
            },
            {
              "byte_inserted": 520693,
              "byte_miss": 520693,
              "byte_read": 74545,
              "byte_reinserted": 74545,
              "hit": 74545,
              "inserted": 520693,
              "miss_ratio": 0.8747643799623008,
              "reinserted": 74545,
              "req": 595238
            },
            {
              "byte_inserted": 520842,
              "byte_miss": 520842,
              "byte_read": 74396,
              "byte_reinserted": 74396,
              "hit": 74396,
              "inserted": 520842,
              "miss_ratio": 0.875014700002352,
              "reinserted": 74396,
              "req": 595238
            },
            {
              "byte_inserted": 520799,
              "byte_miss": 520799,
              "byte_read": 74439,
              "byte_reinserted": 74439,
              "hit": 74439,
              "inserted": 520799,
              "miss_ratio": 0.8749424599907936,
              "reinserted": 74439,
              "req": 595238
            },
            {
              "byte_inserted": 520824,
              "byte_miss": 520824,
              "byte_read": 74414,
              "byte_reinserted": 74414,
              "hit": 74414,
              "inserted": 520824,
              "miss_ratio": 0.8749844599975136,
              "reinserted": 74414,
              "req": 595238
            },
            {
              "byte_inserted": 520826,
              "byte_miss": 520826,
              "byte_read": 74412,
              "byte_reinserted": 74412,
              "hit": 74412,
              "inserted": 520826,
              "miss_ratio": 0.8749878199980512,
              "reinserted": 74412,
              "req": 595238
            },
            {
              "byte_inserted": 521111,
              "byte_miss": 521111,
              "byte_read": 74127,
              "byte_reinserted": 74127,
              "hit": 74127,
              "inserted": 521111,
              "miss_ratio": 0.8754666200746593,
              "reinserted": 74127,
              "req": 595238
            },
            {
              "byte_inserted": 520579,
              "byte_miss": 520579,
              "byte_read": 74659,
              "byte_reinserted": 74659,
              "hit": 74659,
              "inserted": 520579,
              "miss_ratio": 0.8745728599316576,
              "reinserted": 74659,
              "req": 595238
            },
            {
              "byte_inserted": 520981,
              "byte_miss": 520981,
              "byte_read": 74257,
              "byte_reinserted": 74257,
              "hit": 74257,
              "inserted": 520981,
              "miss_ratio": 0.8752482200397153,
              "reinserted": 74257,
              "req": 595238
            },
            {
              "byte_inserted": 520766,
              "byte_miss": 520766,
              "byte_read": 74472,
              "byte_reinserted": 74472,
              "hit": 74472,
              "inserted": 520766,
              "miss_ratio": 0.8748870199819232,
              "reinserted": 74472,
              "req": 595238
            },
            {
              "byte_inserted": 520731,
              "byte_miss": 520731,
              "byte_read": 74508,
              "byte_reinserted": 74508,
              "hit": 74508,
              "inserted": 520731,
              "miss_ratio": 0.8748267502633396,
              "reinserted": 74508,
              "req": 595239
            },
            {
              "byte_inserted": 521031,
              "byte_miss": 521031,
              "byte_read": 74207,
              "byte_reinserted": 74207,
              "hit": 74207,
              "inserted": 521031,
              "miss_ratio": 0.8753322200531553,
              "reinserted": 74207,
              "req": 595238
            },
            {
              "byte_inserted": 520940,
              "byte_miss": 520940,
              "byte_read": 74298,
              "byte_reinserted": 74298,
              "hit": 74298,
              "inserted": 520940,
              "miss_ratio": 0.8751793400286945,
              "reinserted": 74298,
              "req": 595238
            },
            {
              "byte_inserted": 520851,
              "byte_miss": 520851,
              "byte_read": 74387,
              "byte_reinserted": 74387,
              "hit": 74387,
              "inserted": 520851,
              "miss_ratio": 0.8750298200047713,
              "reinserted": 74387,
              "req": 595238
            },
            {
              "byte_inserted": 521118,
              "byte_miss": 521118,
              "byte_read": 74120,
              "byte_reinserted": 74120,
              "hit": 74120,
              "inserted": 521118,
              "miss_ratio": 0.8754783800765408,
              "reinserted": 74120,
              "req": 595238
            },
            {
              "byte_inserted": 520589,
              "byte_miss": 520589,
              "byte_read": 74649,
              "byte_reinserted": 74649,
              "hit": 74649,
              "inserted": 520589,
              "miss_ratio": 0.8745896599343456,
              "reinserted": 74649,
              "req": 595238
            },
            {
              "byte_inserted": 521215,
              "byte_miss": 521215,
              "byte_read": 74023,
              "byte_reinserted": 74023,
              "hit": 74023,
              "inserted": 521215,
              "miss_ratio": 0.8756413401026144,
              "reinserted": 74023,
              "req": 595238
            },
            {
              "byte_inserted": 520910,
              "byte_miss": 520910,
              "byte_read": 74328,
              "byte_reinserted": 74328,
              "hit": 74328,
              "inserted": 520910,
              "miss_ratio": 0.8751289400206304,
              "reinserted": 74328,
              "req": 595238
            },
            {
              "byte_inserted": 520759,
              "byte_miss": 520759,
              "byte_read": 74479,
              "byte_reinserted": 74479,
              "hit": 74479,
              "inserted": 520759,
              "miss_ratio": 0.8748752599800416,
              "reinserted": 74479,
              "req": 595238
            },
            {
              "byte_inserted": 520367,
              "byte_miss": 520367,
              "byte_read": 74871,
              "byte_reinserted": 74871,
              "hit": 74871,
              "inserted": 520367,
              "miss_ratio": 0.874216699874672,
              "reinserted": 74871,
              "req": 595238
            },
            {
              "byte_inserted": 520821,
              "byte_miss": 520821,
              "byte_read": 74418,
              "byte_reinserted": 74418,
              "hit": 74418,
              "inserted": 520821,
              "miss_ratio": 0.874977950033516,
              "reinserted": 74418,
              "req": 595239
            },
            {
              "byte_inserted": 521210,
              "byte_miss": 521210,
              "byte_read": 74028,
              "byte_reinserted": 74028,
              "hit": 74028,
              "inserted": 521210,
              "miss_ratio": 0.8756329401012705,
              "reinserted": 74028,
              "req": 595238
            },
            {
              "byte_inserted": 520990,
              "byte_miss": 520990,
              "byte_read": 74248,
              "byte_reinserted": 74248,
              "hit": 74248,
              "inserted": 520990,
              "miss_ratio": 0.8752633400421344,
              "reinserted": 74248,
              "req": 595238
            },
            {
              "byte_inserted": 520677,
              "byte_miss": 520677,
              "byte_read": 74561,
              "byte_reinserted": 74561,
              "hit": 74561,
              "inserted": 520677,
              "miss_ratio": 0.874737499958,
              "reinserted": 74561,
              "req": 595238
            },
            {
              "byte_inserted": 520495,
              "byte_miss": 520495,
              "byte_read": 74743,
              "byte_reinserted": 74743,
              "hit": 74743,
              "inserted": 520495,
              "miss_ratio": 0.8744317399090784,
              "reinserted": 74743,
              "req": 595238
            },
            {
              "byte_inserted": 521175,
              "byte_miss": 521175,
              "byte_read": 74063,
              "byte_reinserted": 74063,
              "hit": 74063,
              "inserted": 521175,
              "miss_ratio": 0.8755741400918624,
              "reinserted": 74063,
              "req": 595238
            },
            {
              "byte_inserted": 520912,
              "byte_miss": 520912,
              "byte_read": 74326,
              "byte_reinserted": 74326,
              "hit": 74326,
              "inserted": 520912,
              "miss_ratio": 0.875132300021168,
              "reinserted": 74326,
              "req": 595238
            },
            {
              "byte_inserted": 520889,
              "byte_miss": 520889,
              "byte_read": 74349,
              "byte_reinserted": 74349,
              "hit": 74349,
              "inserted": 520889,
              "miss_ratio": 0.8750936600149856,
              "reinserted": 74349,
              "req": 595238
            },
            {
              "byte_inserted": 520627,
              "byte_miss": 520627,
              "byte_read": 74611,
              "byte_reinserted": 74611,
              "hit": 74611,
              "inserted": 520627,
              "miss_ratio": 0.87465349994456,
              "reinserted": 74611,
              "req": 595238
            },
            {
              "byte_inserted": 520733,
              "byte_miss": 520733,
              "byte_read": 74505,
              "byte_reinserted": 74505,
              "hit": 74505,
              "inserted": 520733,
              "miss_ratio": 0.8748315799730528,
              "reinserted": 74505,
              "req": 595238
            },
            {
              "byte_inserted": 520513,
              "byte_miss": 520513,
              "byte_read": 74725,
              "byte_reinserted": 74725,
              "hit": 74725,
              "inserted": 520513,
              "miss_ratio": 0.8744619799139168,
              "reinserted": 74725,
              "req": 595238
            },
            {
              "byte_inserted": 520213,
              "byte_miss": 520213,
              "byte_read": 75026,
              "byte_reinserted": 75026,
              "hit": 75026,
              "inserted": 520213,
              "miss_ratio": 0.8739565115861023,
              "reinserted": 75026,
              "req": 595239
            },
            {
              "byte_inserted": 521020,
              "byte_miss": 521020,
              "byte_read": 74218,
              "byte_reinserted": 74218,
              "hit": 74218,
              "inserted": 521020,
              "miss_ratio": 0.8753137400501985,
              "reinserted": 74218,
              "req": 595238
            },
            {
              "byte_inserted": 520438,
              "byte_miss": 520438,
              "byte_read": 74800,
              "byte_reinserted": 74800,
              "hit": 74800,
              "inserted": 520438,
              "miss_ratio": 0.8743359798937568,
              "reinserted": 74800,
              "req": 595238
            },
            {
              "byte_inserted": 520977,
              "byte_miss": 520977,
              "byte_read": 74261,
              "byte_reinserted": 74261,
              "hit": 74261,
              "inserted": 520977,
              "miss_ratio": 0.87524150003864,
              "reinserted": 74261,
              "req": 595238
            },
            {
              "byte_inserted": 520654,
              "byte_miss": 520654,
              "byte_read": 74584,
              "byte_reinserted": 74584,
              "hit": 74584,
              "inserted": 520654,
              "miss_ratio": 0.8746988599518176,
              "reinserted": 74584,
              "req": 595238
            },
            {
              "byte_inserted": 520538,
              "byte_miss": 520538,
              "byte_read": 74700,
              "byte_reinserted": 74700,
              "hit": 74700,
              "inserted": 520538,
              "miss_ratio": 0.8745039799206368,
              "reinserted": 74700,
              "req": 595238
            },
            {
              "byte_inserted": 521260,
              "byte_miss": 521260,
              "byte_read": 73978,
              "byte_reinserted": 73978,
              "hit": 73978,
              "inserted": 521260,
              "miss_ratio": 0.8757169401147105,
              "reinserted": 73978,
              "req": 595238
            },
            {
              "byte_inserted": 520760,
              "byte_miss": 520760,
              "byte_read": 74478,
              "byte_reinserted": 74478,
              "hit": 74478,
              "inserted": 520760,
              "miss_ratio": 0.8748769399803105,
              "reinserted": 74478,
              "req": 595238
            },
            {
              "byte_inserted": 521007,
              "byte_miss": 521007,
              "byte_read": 74231,
              "byte_reinserted": 74231,
              "hit": 74231,
              "inserted": 521007,
              "miss_ratio": 0.875291900046704,
              "reinserted": 74231,
              "req": 595238
            },
            {
              "byte_inserted": 520828,
              "byte_miss": 520828,
              "byte_read": 74410,
              "byte_reinserted": 74410,
              "hit": 74410,
              "inserted": 520828,
              "miss_ratio": 0.8749911799985888,
              "reinserted": 74410,
              "req": 595238
            },
            {
              "byte_inserted": 520660,
              "byte_miss": 520660,
              "byte_read": 74579,
              "byte_reinserted": 74579,
              "hit": 74579,
              "inserted": 520660,
              "miss_ratio": 0.8747074704446449,
              "reinserted": 74579,
              "req": 595239
            },
            {
              "byte_inserted": 520935,
              "byte_miss": 520935,
              "byte_read": 74303,
              "byte_reinserted": 74303,
              "hit": 74303,
              "inserted": 520935,
              "miss_ratio": 0.8751709400273504,
              "reinserted": 74303,
              "req": 595238
            },
            {
              "byte_inserted": 520681,
              "byte_miss": 520681,
              "byte_read": 74557,
              "byte_reinserted": 74557,
              "hit": 74557,
              "inserted": 520681,
              "miss_ratio": 0.8747442199590751,
              "reinserted": 74557,
              "req": 595238
            },
            {
              "byte_inserted": 520678,
              "byte_miss": 520678,
              "byte_read": 74560,
              "byte_reinserted": 74560,
              "hit": 74560,
              "inserted": 520678,
              "miss_ratio": 0.8747391799582688,
              "reinserted": 74560,
              "req": 595238
            },
            {
              "byte_inserted": 520731,
              "byte_miss": 520731,
              "byte_read": 74507,
              "byte_reinserted": 74507,
              "hit": 74507,
              "inserted": 520731,
              "miss_ratio": 0.8748282199725153,
              "reinserted": 74507,
              "req": 595238
            },
            {
              "byte_inserted": 521411,
              "byte_miss": 521411,
              "byte_read": 73827,
              "byte_reinserted": 73827,
              "hit": 73827,
              "inserted": 521411,
              "miss_ratio": 0.8759706201552993,
              "reinserted": 73827,
              "req": 595238
            },
            {
              "byte_inserted": 520773,
              "byte_miss": 520773,
              "byte_read": 74465,
              "byte_reinserted": 74465,
              "hit": 74465,
              "inserted": 520773,
              "miss_ratio": 0.8748987799838048,
              "reinserted": 74465,
              "req": 595238
            },
            {
              "byte_inserted": 520411,
              "byte_miss": 520411,
              "byte_read": 74827,
              "byte_reinserted": 74827,
              "hit": 74827,
              "inserted": 520411,
              "miss_ratio": 0.8742906198864991,
              "reinserted": 74827,
              "req": 595238
            },
            {
              "byte_inserted": 521198,
              "byte_miss": 521198,
              "byte_read": 74040,
              "byte_reinserted": 74040,
              "hit": 74040,
              "inserted": 521198,
              "miss_ratio": 0.8756127800980448,
              "reinserted": 74040,
              "req": 595238
            },
            {
              "byte_inserted": 520731,
              "byte_miss": 520731,
              "byte_read": 74507,
              "byte_reinserted": 74507,
              "hit": 74507,
              "inserted": 520731,
              "miss_ratio": 0.8748282199725153,
              "reinserted": 74507,
              "req": 595238
            },
            {
              "byte_inserted": 520996,
              "byte_miss": 520996,
              "byte_read": 74242,
              "byte_reinserted": 74242,
              "hit": 74242,
              "inserted": 520996,
              "miss_ratio": 0.8752734200437472,
              "reinserted": 74242,
              "req": 595238
            }
          ],
          "miss_ratio": 0.87516956,
          "reinserted": 6241522,
          "req": 50000000
        },
        {
          "admission_treshold": 32,
          "algorithm": "fifo",
          "byte_inserted": 7621253,
          "byte_miss": 33919539,
          "byte_read": 9838939,
          "byte_reinserted": 0,
          "hit": 9838939,
          "inserted": 7621253,
          "layer": 1,
          "metrics_time": [
            {
              "byte_inserted": 0,
              "byte_miss": 529109,
              "byte_read": 0,
              "byte_reinserted": 0,
              "hit": 0,
              "inserted": 0,
              "miss_ratio": 1.0,
              "reinserted": 0,
              "req": 529109
            },
            {
              "byte_inserted": 0,
              "byte_miss": 521187,
              "byte_read": 0,
              "byte_reinserted": 0,
              "hit": 0,
              "inserted": 0,
              "miss_ratio": 1.0,
              "reinserted": 0,
              "req": 521187
            },
            {
              "byte_inserted": 0,
              "byte_miss": 520836,
              "byte_read": 0,
              "byte_reinserted": 0,
              "hit": 0,
              "inserted": 0,
              "miss_ratio": 1.0,
              "reinserted": 0,
              "req": 520836
            },
            {
              "byte_inserted": 0,
              "byte_miss": 520846,
              "byte_read": 0,
              "byte_reinserted": 0,
              "hit": 0,
              "inserted": 0,
              "miss_ratio": 1.0,
              "reinserted": 0,
              "req": 520846
            },
            {
              "byte_inserted": 0,
              "byte_miss": 520831,
              "byte_read": 0,
              "byte_reinserted": 0,
              "hit": 0,
              "inserted": 0,
              "miss_ratio": 1.0,
              "reinserted": 0,
              "req": 520831
            },
            {
              "byte_inserted": 0,
              "byte_miss": 521254,
              "byte_read": 0,
              "byte_reinserted": 0,
              "hit": 0,
              "inserted": 0,
              "miss_ratio": 1.0,
              "reinserted": 0,
              "req": 521254
            },
            {
              "byte_inserted": 0,
              "byte_miss": 521302,
              "byte_read": 0,
              "byte_reinserted": 0,
              "hit": 0,
              "inserted": 0,
              "miss_ratio": 1.0,
              "reinserted": 0,
              "req": 521302
            },
            {
              "byte_inserted": 0,
              "byte_miss": 521083,
              "byte_read": 0,
              "byte_reinserted": 0,
              "hit": 0,
              "inserted": 0,
              "miss_ratio": 1.0,
              "reinserted": 0,
              "req": 521083
            },
            {
              "byte_inserted": 0,
              "byte_miss": 520943,
              "byte_read": 0,
              "byte_reinserted": 0,
              "hit": 0,
              "inserted": 0,
              "miss_ratio": 1.0,
              "reinserted": 0,
              "req": 520943
            },
            {
              "byte_inserted": 0,
              "byte_miss": 520927,
              "byte_read": 0,
              "byte_reinserted": 0,
              "hit": 0,
              "inserted": 0,
              "miss_ratio": 1.0,
              "reinserted": 0,
              "req": 520927
            },
            {
              "byte_inserted": 0,
              "byte_miss": 520711,
              "byte_read": 0,
              "byte_reinserted": 0,
              "hit": 0,
              "inserted": 0,
              "miss_ratio": 1.0,
              "reinserted": 0,
              "req": 520711
            },
            {
              "byte_inserted": 0,
              "byte_miss": 520433,
              "byte_read": 0,
              "byte_reinserted": 0,
              "hit": 0,
              "inserted": 0,
              "miss_ratio": 1.0,
              "reinserted": 0,
              "req": 520433
            },
            {
              "byte_inserted": 0,
              "byte_miss": 521040,
              "byte_read": 0,
              "byte_reinserted": 0,
              "hit": 0,
              "inserted": 0,
              "miss_ratio": 1.0,
              "reinserted": 0,
              "req": 521040
            },
            {
              "byte_inserted": 0,
              "byte_miss": 520761,
              "byte_read": 0,
              "byte_reinserted": 0,
              "hit": 0,
              "inserted": 0,
              "miss_ratio": 1.0,
              "reinserted": 0,
              "req": 520761
            },
            {
              "byte_inserted": 0,
              "byte_miss": 520807,
              "byte_read": 0,
              "byte_reinserted": 0,
              "hit": 0,
              "inserted": 0,
              "miss_ratio": 1.0,
              "reinserted": 0,
              "req": 520807
            },
            {
              "byte_inserted": 0,
              "byte_miss": 520971,
              "byte_read": 0,
              "byte_reinserted": 0,
              "hit": 0,
              "inserted": 0,
              "miss_ratio": 1.0,
              "reinserted": 0,
              "req": 520971
            },
            {
              "byte_inserted": 0,
              "byte_miss": 520969,
              "byte_read": 0,
              "byte_reinserted": 0,
              "hit": 0,
              "inserted": 0,
              "miss_ratio": 1.0,
              "reinserted": 0,
              "req": 520969
            },
            {
              "byte_inserted": 0,
              "byte_miss": 520952,
              "byte_read": 0,
              "byte_reinserted": 0,
              "hit": 0,
              "inserted": 0,
              "miss_ratio": 1.0,
              "reinserted": 0,
              "req": 520952
            },
            {
              "byte_inserted": 0,
              "byte_miss": 521055,
              "byte_read": 0,
              "byte_reinserted": 0,
              "hit": 0,
              "inserted": 0,
              "miss_ratio": 1.0,
              "reinserted": 0,
              "req": 521055
            },
            {
              "byte_inserted": 0,
              "byte_miss": 520899,
              "byte_read": 0,
              "byte_reinserted": 0,
              "hit": 0,
              "inserted": 0,
              "miss_ratio": 1.0,
              "reinserted": 0,
              "req": 520899
            },
            {
              "byte_inserted": 2,
              "byte_miss": 520925,
              "byte_read": 0,
              "byte_reinserted": 0,
              "hit": 0,
              "inserted": 2,
              "miss_ratio": 1.0,
              "reinserted": 0,
              "req": 520925
            },
            {
              "byte_inserted": 0,
              "byte_miss": 520658,
              "byte_read": 0,
              "byte_reinserted": 0,
              "hit": 0,
              "inserted": 0,
              "miss_ratio": 1.0,
              "reinserted": 0,
              "req": 520658
            },
            {
              "byte_inserted": 9,
              "byte_miss": 520730,
              "byte_read": 3,
              "byte_reinserted": 0,
              "hit": 3,
              "inserted": 9,
              "miss_ratio": 0.9999942388901798,
              "reinserted": 0,
              "req": 520733
            },
            {
              "byte_inserted": 16,
              "byte_miss": 520426,
              "byte_read": 14,
              "byte_reinserted": 0,
              "hit": 14,
              "inserted": 16,
              "miss_ratio": 0.999973099684882,
              "reinserted": 0,
              "req": 520440
            },
            {
              "byte_inserted": 34,
              "byte_miss": 520285,
              "byte_read": 20,
              "byte_reinserted": 0,
              "hit": 20,
              "inserted": 34,
              "miss_ratio": 0.999961561007486,
              "reinserted": 0,
              "req": 520305
            },
            {
              "byte_inserted": 58,
              "byte_miss": 520926,
              "byte_read": 39,
              "byte_reinserted": 0,
              "hit": 39,
              "inserted": 58,
              "miss_ratio": 0.9999251389248798,
              "reinserted": 0,
              "req": 520965
            },
            {
              "byte_inserted": 119,
              "byte_miss": 520693,
              "byte_read": 92,
              "byte_reinserted": 0,
              "hit": 92,
              "inserted": 119,
              "miss_ratio": 0.9998233436062867,
              "reinserted": 0,
              "req": 520785
            },
            {
              "byte_inserted": 215,
              "byte_miss": 520740,
              "byte_read": 186,
              "byte_reinserted": 0,
              "hit": 186,
              "inserted": 215,
              "miss_ratio": 0.9996429435274876,
              "reinserted": 0,
              "req": 520926
            },
            {
              "byte_inserted": 355,
              "byte_miss": 520981,
              "byte_read": 315,
              "byte_reinserted": 0,
              "hit": 315,
              "inserted": 355,
              "miss_ratio": 0.9993957367791044,
              "reinserted": 0,
              "req": 521296
            },
            {
              "byte_inserted": 550,
              "byte_miss": 520239,
              "byte_read": 521,
              "byte_reinserted": 0,
              "hit": 521,
              "inserted": 550,
              "miss_ratio": 0.9989995391351102,
              "reinserted": 0,
              "req": 520760
            },
            {
              "byte_inserted": 930,
              "byte_miss": 519873,
              "byte_read": 940,
              "byte_reinserted": 0,
              "hit": 940,
              "inserted": 930,
              "miss_ratio": 0.9981951295378572,
              "reinserted": 0,
              "req": 520813
            },
            {
              "byte_inserted": 1371,
              "byte_miss": 518805,
              "byte_read": 1517,
              "byte_reinserted": 0,
              "hit": 1517,
              "inserted": 1371,
              "miss_ratio": 0.9970844976764388,
              "reinserted": 0,
              "req": 520322
            },
            {
              "byte_inserted": 1962,
              "byte_miss": 518343,
              "byte_read": 2417,
              "byte_reinserted": 0,
              "hit": 2417,
              "inserted": 1962,
              "miss_ratio": 0.995358706505876,
              "reinserted": 0,
              "req": 520760
            },
            {
              "byte_inserted": 2888,
              "byte_miss": 517097,
              "byte_read": 3596,
              "byte_reinserted": 0,
              "hit": 3596,
              "inserted": 2888,
              "miss_ratio": 0.9930938191986449,
              "reinserted": 0,
              "req": 520693
            },
            {
              "byte_inserted": 3987,
              "byte_miss": 515311,
              "byte_read": 5531,
              "byte_reinserted": 0,
              "hit": 5531,
              "inserted": 3987,
              "miss_ratio": 0.9893806567058724,
              "reinserted": 0,
              "req": 520842
            },
            {
              "byte_inserted": 5392,
              "byte_miss": 512962,
              "byte_read": 7837,
              "byte_reinserted": 0,
              "hit": 7837,
              "inserted": 5392,
              "miss_ratio": 0.9849519680337327,
              "reinserted": 0,
              "req": 520799
            },
            {
              "byte_inserted": 6995,
              "byte_miss": 509719,
              "byte_read": 11105,
              "byte_reinserted": 0,
              "hit": 11105,
              "inserted": 6995,
              "miss_ratio": 0.9786780179100809,
              "reinserted": 0,
              "req": 520824
            },
            {
              "byte_inserted": 9098,
              "byte_miss": 505601,
              "byte_read": 15225,
              "byte_reinserted": 0,
              "hit": 15225,
              "inserted": 9098,
              "miss_ratio": 0.9707675884076448,
              "reinserted": 0,
              "req": 520826
            },
            {
              "byte_inserted": 11220,
              "byte_miss": 500637,
              "byte_read": 20474,
              "byte_reinserted": 0,
              "hit": 20474,
              "inserted": 11220,
              "miss_ratio": 0.9607108658232123,
              "reinserted": 0,
              "req": 521111
            },
            {
              "byte_inserted": 13490,
              "byte_miss": 493809,
              "byte_read": 26770,
              "byte_reinserted": 0,
              "hit": 26770,
              "inserted": 13490,
              "miss_ratio": 0.9485764888710455,
              "reinserted": 0,
              "req": 520579
            },
            {
              "byte_inserted": 16562,
              "byte_miss": 486023,
              "byte_read": 34958,
              "byte_reinserted": 0,
              "hit": 34958,
              "inserted": 16562,
              "miss_ratio": 0.9328996642871813,
              "reinserted": 0,
              "req": 520981
            },
            {
              "byte_inserted": 19810,
              "byte_miss": 476592,
              "byte_read": 44174,
              "byte_reinserted": 0,
              "hit": 44174,
              "inserted": 19810,
              "miss_ratio": 0.9151749538180296,
              "reinserted": 0,
              "req": 520766
            },
            {
              "byte_inserted": 22557,
              "byte_miss": 464830,
              "byte_read": 55901,
              "byte_reinserted": 0,
              "hit": 55901,
              "inserted": 22557,
              "miss_ratio": 0.892648987673098,
              "reinserted": 0,
              "req": 520731
            },
            {
              "byte_inserted": 25959,
              "byte_miss": 452999,
              "byte_read": 68032,
              "byte_reinserted": 0,
              "hit": 68032,
              "inserted": 25959,
              "miss_ratio": 0.8694281146419311,
              "reinserted": 0,
              "req": 521031
            },
            {
              "byte_inserted": 28624,
              "byte_miss": 438564,
              "byte_read": 82376,
              "byte_reinserted": 0,
              "hit": 82376,
              "inserted": 28624,
              "miss_ratio": 0.8418704649287826,
              "reinserted": 0,
              "req": 520940
            },
            {
              "byte_inserted": 31746,
              "byte_miss": 422535,
              "byte_read": 98316,
              "byte_reinserted": 0,
              "hit": 98316,
              "inserted": 31746,
              "miss_ratio": 0.811239682749961,
              "reinserted": 0,
              "req": 520851
            },
            {
              "byte_inserted": 34568,
              "byte_miss": 405507,
              "byte_read": 115611,
              "byte_reinserted": 0,
              "hit": 115611,
              "inserted": 34568,
              "miss_ratio": 0.7781481353551403,
              "reinserted": 0,
              "req": 521118
            },
            {
              "byte_inserted": 36813,
              "byte_miss": 386416,
              "byte_read": 134173,
              "byte_reinserted": 0,
              "hit": 134173,
              "inserted": 36813,
              "miss_ratio": 0.7422669322632633,
              "reinserted": 0,
              "req": 520589
            },
            {
              "byte_inserted": 38756,
              "byte_miss": 367513,
              "byte_read": 153702,
              "byte_reinserted": 0,
              "hit": 153702,
              "inserted": 38756,
              "miss_ratio": 0.7051082566695126,
              "reinserted": 0,
              "req": 521215
            },
            {
              "byte_inserted": 40577,
              "byte_miss": 346770,
              "byte_read": 174140,
              "byte_reinserted": 0,
              "hit": 174140,
              "inserted": 40577,
              "miss_ratio": 0.66570040889981,
              "reinserted": 0,
              "req": 520910
            },
            {
              "byte_inserted": 41737,
              "byte_miss": 324691,
              "byte_read": 196068,
              "byte_reinserted": 0,
              "hit": 196068,
              "inserted": 41737,
              "miss_ratio": 0.6234957053070614,
              "reinserted": 0,
              "req": 520759
            },
            {
              "byte_inserted": 42504,
              "byte_miss": 303014,
              "byte_read": 217353,
              "byte_reinserted": 0,
              "hit": 217353,
              "inserted": 42504,
              "miss_ratio": 0.5823082555196621,
              "reinserted": 0,
              "req": 520367
            },
            {
              "byte_inserted": 42248,
              "byte_miss": 280294,
              "byte_read": 240527,
              "byte_reinserted": 0,
              "hit": 240527,
              "inserted": 42248,
              "miss_ratio": 0.5381772240366651,
              "reinserted": 0,
              "req": 520821
            },
            {
              "byte_inserted": 45584,
              "byte_miss": 262933,
              "byte_read": 258277,
              "byte_reinserted": 0,
              "hit": 258277,
              "inserted": 45584,
              "miss_ratio": 0.5044665298056445,
              "reinserted": 0,
              "req": 521210
            },
            {
              "byte_inserted": 67055,
              "byte_miss": 260136,
              "byte_read": 260854,
              "byte_reinserted": 0,
              "hit": 260854,
              "inserted": 67055,
              "miss_ratio": 0.49931092727307624,
              "reinserted": 0,
              "req": 520990
            },
            {
              "byte_inserted": 90055,
              "byte_miss": 259867,
              "byte_read": 260810,
              "byte_reinserted": 0,
              "hit": 260810,
              "inserted": 90055,
              "miss_ratio": 0.4990944481895686,
              "reinserted": 0,
              "req": 520677
            },
            {
              "byte_inserted": 111895,
              "byte_miss": 259474,
              "byte_read": 261021,
              "byte_reinserted": 0,
              "hit": 261021,
              "inserted": 111895,
              "miss_ratio": 0.49851391463894945,
              "reinserted": 0,
              "req": 520495
            },
            {
              "byte_inserted": 132244,
              "byte_miss": 259770,
              "byte_read": 261405,
              "byte_reinserted": 0,
              "hit": 261405,
              "inserted": 132244,
              "miss_ratio": 0.4984314289825874,
              "reinserted": 0,
              "req": 521175
            },
            {
              "byte_inserted": 151748,
              "byte_miss": 259843,
              "byte_read": 261069,
              "byte_reinserted": 0,
              "hit": 261069,
              "inserted": 151748,
              "miss_ratio": 0.4988232177411923,
              "reinserted": 0,
              "req": 520912
            },
            {
              "byte_inserted": 168562,
              "byte_miss": 258866,
              "byte_read": 262023,
              "byte_reinserted": 0,
              "hit": 262023,
              "inserted": 168562,
              "miss_ratio": 0.49696960388873634,
              "reinserted": 0,
              "req": 520889
            },
            {
              "byte_inserted": 185108,
              "byte_miss": 258631,
              "byte_read": 261996,
              "byte_reinserted": 0,
              "hit": 261996,
              "inserted": 185108,
              "miss_ratio": 0.4967683197375472,
              "reinserted": 0,
              "req": 520627
            },
            {
              "byte_inserted": 199531,
              "byte_miss": 259101,
              "byte_read": 261632,
              "byte_reinserted": 0,
              "hit": 261632,
              "inserted": 199531,
              "miss_ratio": 0.4975697718408474,
              "reinserted": 0,
              "req": 520733
            },
            {
              "byte_inserted": 213151,
              "byte_miss": 258570,
              "byte_read": 261943,
              "byte_reinserted": 0,
              "hit": 261943,
              "inserted": 213151,
              "miss_ratio": 0.4967599272256409,
              "reinserted": 0,
              "req": 520513
            },
            {
              "byte_inserted": 224312,
              "byte_miss": 258043,
              "byte_read": 262170,
              "byte_reinserted": 0,
              "hit": 262170,
              "inserted": 224312,
              "miss_ratio": 0.49603335556781547,
              "reinserted": 0,
              "req": 520213
            },
            {
              "byte_inserted": 234495,
              "byte_miss": 258670,
              "byte_read": 262350,
              "byte_reinserted": 0,
              "hit": 262350,
              "inserted": 234495,
              "miss_ratio": 0.4964684657018924,
              "reinserted": 0,
              "req": 521020
            },
            {
              "byte_inserted": 244077,
              "byte_miss": 258192,
              "byte_read": 262246,
              "byte_reinserted": 0,
              "hit": 262246,
              "inserted": 244077,
              "miss_ratio": 0.4961052036938117,
              "reinserted": 0,
              "req": 520438
            },
            {
              "byte_inserted": 252173,
              "byte_miss": 258261,
              "byte_read": 262716,
              "byte_reinserted": 0,
              "hit": 262716,
              "inserted": 252173,
              "miss_ratio": 0.49572437938718983,
              "reinserted": 0,
              "req": 520977
            },
            {
              "byte_inserted": 258645,
              "byte_miss": 258067,
              "byte_read": 262587,
              "byte_reinserted": 0,
              "hit": 262587,
              "inserted": 258645,
              "miss_ratio": 0.4956593054120395,
              "reinserted": 0,
              "req": 520654
            },
            {
              "byte_inserted": 265253,
              "byte_miss": 258334,
              "byte_read": 262204,
              "byte_reinserted": 0,
              "hit": 262204,
              "inserted": 265253,
              "miss_ratio": 0.4962826921377498,
              "reinserted": 0,
              "req": 520538
            },
            {
              "byte_inserted": 270401,
              "byte_miss": 258493,
              "byte_read": 262767,
              "byte_reinserted": 0,
              "hit": 262767,
              "inserted": 270401,
              "miss_ratio": 0.4959003184591183,
              "reinserted": 0,
              "req": 521260
            },
            {
              "byte_inserted": 274663,
              "byte_miss": 258573,
              "byte_read": 262187,
              "byte_reinserted": 0,
              "hit": 262187,
              "inserted": 274663,
              "miss_ratio": 0.4965300714340579,
              "reinserted": 0,
              "req": 520760
            },
            {
              "byte_inserted": 277748,
              "byte_miss": 257785,
              "byte_read": 263222,
              "byte_reinserted": 0,
              "hit": 263222,
              "inserted": 277748,
              "miss_ratio": 0.4947822198166243,
              "reinserted": 0,
              "req": 521007
            },
            {
              "byte_inserted": 280880,
              "byte_miss": 258333,
              "byte_read": 262495,
              "byte_reinserted": 0,
              "hit": 262495,
              "inserted": 280880,
              "miss_ratio": 0.4960044390854562,
              "reinserted": 0,
              "req": 520828
            },
            {
              "byte_inserted": 283714,
              "byte_miss": 257796,
              "byte_read": 262864,
              "byte_reinserted": 0,
              "hit": 262864,
              "inserted": 283714,
              "miss_ratio": 0.4951331002957784,
              "reinserted": 0,
              "req": 520660
            },
            {
              "byte_inserted": 286043,
              "byte_miss": 258789,
              "byte_read": 262146,
              "byte_reinserted": 0,
              "hit": 262146,
              "inserted": 286043,
              "miss_ratio": 0.49677790895217255,
              "reinserted": 0,
              "req": 520935
            },
            {
              "byte_inserted": 287658,
              "byte_miss": 258186,
              "byte_read": 262495,
              "byte_reinserted": 0,
              "hit": 262495,
              "inserted": 287658,
              "miss_ratio": 0.4958621497615623,
              "reinserted": 0,
              "req": 520681
            },
            {
              "byte_inserted": 289309,
              "byte_miss": 258189,
              "byte_read": 262489,
              "byte_reinserted": 0,
              "hit": 262489,
              "inserted": 289309,
              "miss_ratio": 0.49587076849799683,
              "reinserted": 0,
              "req": 520678
            },
            {
              "byte_inserted": 289932,
              "byte_miss": 257649,
              "byte_read": 263082,
              "byte_reinserted": 0,
              "hit": 263082,
              "inserted": 289932,
              "miss_ratio": 0.49478329502180585,
              "reinserted": 0,
              "req": 520731
            },
            {
              "byte_inserted": 291336,
              "byte_miss": 257996,
              "byte_read": 263415,
              "byte_reinserted": 0,
              "hit": 263415,
              "inserted": 291336,
              "miss_ratio": 0.494803523515998,
              "reinserted": 0,
              "req": 521411
            },
            {
              "byte_inserted": 291653,
              "byte_miss": 258152,
              "byte_read": 262621,
              "byte_reinserted": 0,
              "hit": 262621,
              "inserted": 291653,
              "miss_ratio": 0.49570926296102136,
              "reinserted": 0,
              "req": 520773
            },
            {
              "byte_inserted": 292490,
              "byte_miss": 257786,
              "byte_read": 262625,
              "byte_reinserted": 0,
              "hit": 262625,
              "inserted": 292490,
              "miss_ratio": 0.4953507900486346,
              "reinserted": 0,
              "req": 520411
            },
            {
              "byte_inserted": 292951,
              "byte_miss": 257897,
              "byte_read": 263301,
              "byte_reinserted": 0,
              "hit": 263301,
              "inserted": 292951,
              "miss_ratio": 0.49481578977663,
              "reinserted": 0,
              "req": 521198
            },
            {
              "byte_inserted": 293637,
              "byte_miss": 257892,
              "byte_read": 262839,
              "byte_reinserted": 0,
              "hit": 262839,
              "inserted": 293637,
              "miss_ratio": 0.4952499467095295,
              "reinserted": 0,
              "req": 520731
            },
            {
              "byte_inserted": 293798,
              "byte_miss": 257841,
              "byte_read": 263155,
              "byte_reinserted": 0,
              "hit": 263155,
              "inserted": 293798,
              "miss_ratio": 0.49490015278428245,
              "reinserted": 0,
              "req": 520996
            }
          ],
          "miss_ratio": 0.7751535371042841,
          "reinserted": 0,
          "req": 43758478
        }
      ],
      "miss_ratio": 0.67839078,
      "req": 50000000
    }
  ],
  "trace": "zipf0.oracleGeneral"
}